[{"index":0,"runtimeInSeconds":236.966,"objectiveValue":-336137.16440992866,"trainingStats":{"dialogs":{"total":200,"correct":0},"responses":{"total":2434,"correct":0}},"devStats":{"dialogs":{"total":200,"correct":0},"responses":{"total":2358,"correct":0}}},{"index":200,"runtimeInSeconds":456.375,"objectiveValue":-9943.689610827638,"trainingStats":{"dialogs":{"total":200,"correct":0},"responses":{"total":2434,"correct":1928}},"devStats":{"dialogs":{"total":200,"correct":0},"responses":{"total":2358,"correct":1849}}},{"index":400,"runtimeInSeconds":672.339,"objectiveValue":-6371.677925435137,"trainingStats":{"dialogs":{"total":200,"correct":0},"responses":{"total":2434,"correct":2111}},"devStats":{"dialogs":{"total":200,"correct":0},"responses":{"total":2358,"correct":2037}}},{"index":600,"runtimeInSeconds":887.485,"objectiveValue":-6124.153867403062,"trainingStats":{"dialogs":{"total":200,"correct":0},"responses":{"total":2434,"correct":2176}},"devStats":{"dialogs":{"total":200,"correct":0},"responses":{"total":2358,"correct":2095}}},{"index":800,"runtimeInSeconds":1101.761,"objectiveValue":-6094.219555755095,"trainingStats":{"dialogs":{"total":200,"correct":1},"responses":{"total":2434,"correct":2210}},"devStats":{"dialogs":{"total":200,"correct":0},"responses":{"total":2358,"correct":2138}}},{"index":1000,"runtimeInSeconds":1317.011,"objectiveValue":-4212.996429174568,"trainingStats":{"dialogs":{"total":200,"correct":3},"responses":{"total":2434,"correct":2211}},"devStats":{"dialogs":{"total":200,"correct":0},"responses":{"total":2358,"correct":2133}}},{"index":1200,"runtimeInSeconds":1532.958,"objectiveValue":-4147.1852588128995,"trainingStats":{"dialogs":{"total":200,"correct":2},"responses":{"total":2434,"correct":2199}},"devStats":{"dialogs":{"total":200,"correct":0},"responses":{"total":2358,"correct":2118}}},{"index":1400,"runtimeInSeconds":1748.801,"objectiveValue":-2499.49047612449,"trainingStats":{"dialogs":{"total":200,"correct":31},"responses":{"total":2434,"correct":2245}},"devStats":{"dialogs":{"total":200,"correct":23},"responses":{"total":2358,"correct":2161}}},{"index":1600,"runtimeInSeconds":1964.175,"objectiveValue":-670.2676317541129,"trainingStats":{"dialogs":{"total":200,"correct":90},"responses":{"total":2434,"correct":2312}},"devStats":{"dialogs":{"total":200,"correct":76},"responses":{"total":2358,"correct":2219}}},{"index":1800,"runtimeInSeconds":2178.029,"objectiveValue":-444.98590456603466,"trainingStats":{"dialogs":{"total":200,"correct":130},"responses":{"total":2434,"correct":2363}},"devStats":{"dialogs":{"total":200,"correct":101},"responses":{"total":2358,"correct":2256}}},{"index":2000,"runtimeInSeconds":2392.768,"objectiveValue":-335.44258925684375,"trainingStats":{"dialogs":{"total":200,"correct":157},"responses":{"total":2434,"correct":2390}},"devStats":{"dialogs":{"total":200,"correct":144},"responses":{"total":2358,"correct":2299}}},{"index":2200,"runtimeInSeconds":2606.564,"objectiveValue":-228.76672242614492,"trainingStats":{"dialogs":{"total":200,"correct":162},"responses":{"total":2434,"correct":2395}},"devStats":{"dialogs":{"total":200,"correct":137},"responses":{"total":2358,"correct":2291}}},{"index":2400,"runtimeInSeconds":2819.832,"objectiveValue":-106.34936092507232,"trainingStats":{"dialogs":{"total":200,"correct":168},"responses":{"total":2434,"correct":2402}},"devStats":{"dialogs":{"total":200,"correct":143},"responses":{"total":2358,"correct":2300}}},{"index":2600,"runtimeInSeconds":3033.087,"objectiveValue":-50.09281272985797,"trainingStats":{"dialogs":{"total":200,"correct":189},"responses":{"total":2434,"correct":2423}},"devStats":{"dialogs":{"total":200,"correct":172},"responses":{"total":2358,"correct":2330}}},{"index":2800,"runtimeInSeconds":3246.81,"objectiveValue":-466.1574711190651,"trainingStats":{"dialogs":{"total":200,"correct":150},"responses":{"total":2434,"correct":2382}},"devStats":{"dialogs":{"total":200,"correct":119},"responses":{"total":2358,"correct":2271}}},{"index":3000,"runtimeInSeconds":3465.389,"objectiveValue":-46.55278465995718,"trainingStats":{"dialogs":{"total":200,"correct":185},"responses":{"total":2434,"correct":2419}},"devStats":{"dialogs":{"total":200,"correct":150},"responses":{"total":2358,"correct":2307}}},{"index":3200,"runtimeInSeconds":3680.69,"objectiveValue":-30.217392300348788,"trainingStats":{"dialogs":{"total":200,"correct":195},"responses":{"total":2434,"correct":2429}},"devStats":{"dialogs":{"total":200,"correct":175},"responses":{"total":2358,"correct":2333}}},{"index":3400,"runtimeInSeconds":3897.15,"objectiveValue":-33.475195381790776,"trainingStats":{"dialogs":{"total":200,"correct":195},"responses":{"total":2434,"correct":2429}},"devStats":{"dialogs":{"total":200,"correct":178},"responses":{"total":2358,"correct":2336}}},{"index":3600,"runtimeInSeconds":4109.85,"objectiveValue":-14.155116401045632,"trainingStats":{"dialogs":{"total":200,"correct":197},"responses":{"total":2434,"correct":2431}},"devStats":{"dialogs":{"total":200,"correct":179},"responses":{"total":2358,"correct":2337}}},{"index":3800,"runtimeInSeconds":4325.724,"objectiveValue":-14.400774294095514,"trainingStats":{"dialogs":{"total":200,"correct":196},"responses":{"total":2434,"correct":2430}},"devStats":{"dialogs":{"total":200,"correct":184},"responses":{"total":2358,"correct":2342}}},{"index":4000,"runtimeInSeconds":4539.68,"objectiveValue":-12.20332530494073,"trainingStats":{"dialogs":{"total":200,"correct":198},"responses":{"total":2434,"correct":2432}},"devStats":{"dialogs":{"total":200,"correct":184},"responses":{"total":2358,"correct":2342}}},{"index":4200,"runtimeInSeconds":4758.565,"objectiveValue":-7.3008203399872755,"trainingStats":{"dialogs":{"total":200,"correct":197},"responses":{"total":2434,"correct":2431}},"devStats":{"dialogs":{"total":200,"correct":181},"responses":{"total":2358,"correct":2339}}},{"index":4400,"runtimeInSeconds":4976.72,"objectiveValue":-12.238576706828624,"trainingStats":{"dialogs":{"total":200,"correct":200},"responses":{"total":2434,"correct":2434}},"devStats":{"dialogs":{"total":200,"correct":191},"responses":{"total":2358,"correct":2349}}},{"index":4600,"runtimeInSeconds":5193.471,"objectiveValue":-4.369709368682744,"trainingStats":{"dialogs":{"total":200,"correct":200},"responses":{"total":2434,"correct":2434}},"devStats":{"dialogs":{"total":200,"correct":180},"responses":{"total":2358,"correct":2338}}},{"index":4800,"runtimeInSeconds":5409.841,"objectiveValue":-3.753174484574038,"trainingStats":{"dialogs":{"total":200,"correct":199},"responses":{"total":2434,"correct":2433}},"devStats":{"dialogs":{"total":200,"correct":186},"responses":{"total":2358,"correct":2344}}},{"index":5000,"runtimeInSeconds":5628.315,"objectiveValue":-283.55856645499017,"trainingStats":{"dialogs":{"total":200,"correct":135},"responses":{"total":2434,"correct":2365}},"devStats":{"dialogs":{"total":200,"correct":112},"responses":{"total":2358,"correct":2267}}},{"index":5200,"runtimeInSeconds":5843.741,"objectiveValue":-57.78876978455879,"trainingStats":{"dialogs":{"total":200,"correct":189},"responses":{"total":2434,"correct":2423}},"devStats":{"dialogs":{"total":200,"correct":168},"responses":{"total":2358,"correct":2326}}},{"index":5400,"runtimeInSeconds":6059.734,"objectiveValue":-39.897563576154184,"trainingStats":{"dialogs":{"total":200,"correct":199},"responses":{"total":2434,"correct":2433}},"devStats":{"dialogs":{"total":200,"correct":180},"responses":{"total":2358,"correct":2337}}},{"index":5600,"runtimeInSeconds":6275.096,"objectiveValue":-12.402360752691454,"trainingStats":{"dialogs":{"total":200,"correct":194},"responses":{"total":2434,"correct":2428}},"devStats":{"dialogs":{"total":200,"correct":174},"responses":{"total":2358,"correct":2332}}},{"index":5800,"runtimeInSeconds":6490.258,"objectiveValue":-2.9967865446304134,"trainingStats":{"dialogs":{"total":200,"correct":198},"responses":{"total":2434,"correct":2432}},"devStats":{"dialogs":{"total":200,"correct":193},"responses":{"total":2358,"correct":2351}}},{"index":6000,"runtimeInSeconds":6706.261,"objectiveValue":-2.1354013383349075,"trainingStats":{"dialogs":{"total":200,"correct":199},"responses":{"total":2434,"correct":2433}},"devStats":{"dialogs":{"total":200,"correct":185},"responses":{"total":2358,"correct":2343}}},{"index":6200,"runtimeInSeconds":6921.133,"objectiveValue":-1.6809750392257166,"trainingStats":{"dialogs":{"total":200,"correct":197},"responses":{"total":2434,"correct":2431}},"devStats":{"dialogs":{"total":200,"correct":192},"responses":{"total":2358,"correct":2350}}},{"index":6400,"runtimeInSeconds":7136.234,"objectiveValue":-4.338613894559932,"trainingStats":{"dialogs":{"total":200,"correct":200},"responses":{"total":2434,"correct":2434}},"devStats":{"dialogs":{"total":200,"correct":192},"responses":{"total":2358,"correct":2350}}},{"index":6600,"runtimeInSeconds":7352.13,"objectiveValue":-4.297241271530001,"trainingStats":{"dialogs":{"total":200,"correct":200},"responses":{"total":2434,"correct":2434}},"devStats":{"dialogs":{"total":200,"correct":188},"responses":{"total":2358,"correct":2346}}},{"index":6800,"runtimeInSeconds":7567.789,"objectiveValue":-3.4513988385943932,"trainingStats":{"dialogs":{"total":200,"correct":200},"responses":{"total":2434,"correct":2434}},"devStats":{"dialogs":{"total":200,"correct":190},"responses":{"total":2358,"correct":2348}}},{"index":7000,"runtimeInSeconds":7784.724,"objectiveValue":-1.0865036209819445,"trainingStats":{"dialogs":{"total":200,"correct":200},"responses":{"total":2434,"correct":2434}},"devStats":{"dialogs":{"total":200,"correct":195},"responses":{"total":2358,"correct":2353}}},{"index":7200,"runtimeInSeconds":8001.074,"objectiveValue":-1.587416815021286,"trainingStats":{"dialogs":{"total":200,"correct":199},"responses":{"total":2434,"correct":2433}},"devStats":{"dialogs":{"total":200,"correct":194},"responses":{"total":2358,"correct":2352}}},{"index":7400,"runtimeInSeconds":8217.37,"objectiveValue":-1.5243573897044962,"trainingStats":{"dialogs":{"total":200,"correct":200},"responses":{"total":2434,"correct":2434}},"devStats":{"dialogs":{"total":200,"correct":190},"responses":{"total":2358,"correct":2348}}},{"index":7600,"runtimeInSeconds":8435.08,"objectiveValue":-1.8973742579921238,"trainingStats":{"dialogs":{"total":200,"correct":200},"responses":{"total":2434,"correct":2434}},"devStats":{"dialogs":{"total":200,"correct":190},"responses":{"total":2358,"correct":2348}}},{"index":7800,"runtimeInSeconds":8651.84,"objectiveValue":-206.79036499977616,"trainingStats":{"dialogs":{"total":200,"correct":189},"responses":{"total":2434,"correct":2423}},"devStats":{"dialogs":{"total":200,"correct":179},"responses":{"total":2358,"correct":2337}}},{"index":8000,"runtimeInSeconds":8866.673,"objectiveValue":-7.065770391317579,"trainingStats":{"dialogs":{"total":200,"correct":192},"responses":{"total":2434,"correct":2426}},"devStats":{"dialogs":{"total":200,"correct":174},"responses":{"total":2358,"correct":2332}}},{"index":8200,"runtimeInSeconds":9082.008,"objectiveValue":-34.62541639511766,"trainingStats":{"dialogs":{"total":200,"correct":152},"responses":{"total":2434,"correct":2382}},"devStats":{"dialogs":{"total":200,"correct":120},"responses":{"total":2358,"correct":2270}}},{"index":8400,"runtimeInSeconds":9294.397,"objectiveValue":-6.787701118435308,"trainingStats":{"dialogs":{"total":200,"correct":198},"responses":{"total":2434,"correct":2432}},"devStats":{"dialogs":{"total":200,"correct":187},"responses":{"total":2358,"correct":2345}}},{"index":8600,"runtimeInSeconds":9509.413,"objectiveValue":-1.7855440825658158,"trainingStats":{"dialogs":{"total":200,"correct":200},"responses":{"total":2434,"correct":2434}},"devStats":{"dialogs":{"total":200,"correct":189},"responses":{"total":2358,"correct":2347}}},{"index":8800,"runtimeInSeconds":9723.265,"objectiveValue":-4.371799352269628,"trainingStats":{"dialogs":{"total":200,"correct":200},"responses":{"total":2434,"correct":2434}},"devStats":{"dialogs":{"total":200,"correct":192},"responses":{"total":2358,"correct":2350}}},{"index":9000,"runtimeInSeconds":9941.33,"objectiveValue":-3.6900404150481196,"trainingStats":{"dialogs":{"total":200,"correct":198},"responses":{"total":2434,"correct":2432}},"devStats":{"dialogs":{"total":200,"correct":191},"responses":{"total":2358,"correct":2349}}},{"index":9200,"runtimeInSeconds":10157.399,"objectiveValue":-3.0534245612772706,"trainingStats":{"dialogs":{"total":200,"correct":198},"responses":{"total":2434,"correct":2432}},"devStats":{"dialogs":{"total":200,"correct":195},"responses":{"total":2358,"correct":2353}}},{"index":9400,"runtimeInSeconds":10373.719,"objectiveValue":-1.2586345754983435,"trainingStats":{"dialogs":{"total":200,"correct":199},"responses":{"total":2434,"correct":2433}},"devStats":{"dialogs":{"total":200,"correct":194},"responses":{"total":2358,"correct":2352}}},{"index":9600,"runtimeInSeconds":10586.784,"objectiveValue":-1.608306264619789,"trainingStats":{"dialogs":{"total":200,"correct":200},"responses":{"total":2434,"correct":2434}},"devStats":{"dialogs":{"total":200,"correct":194},"responses":{"total":2358,"correct":2352}}},{"index":9800,"runtimeInSeconds":10803.747,"objectiveValue":-0.8952805187903203,"trainingStats":{"dialogs":{"total":200,"correct":200},"responses":{"total":2434,"correct":2434}},"devStats":{"dialogs":{"total":200,"correct":196},"responses":{"total":2358,"correct":2354}}},{"index":10000,"runtimeInSeconds":11021.98,"objectiveValue":-1.3399701034085743,"trainingStats":{"dialogs":{"total":200,"correct":200},"responses":{"total":2434,"correct":2434}},"devStats":{"dialogs":{"total":200,"correct":192},"responses":{"total":2358,"correct":2350}}},{"index":10200,"runtimeInSeconds":11239.214,"objectiveValue":-16.025233523197517,"trainingStats":{"dialogs":{"total":200,"correct":194},"responses":{"total":2434,"correct":2428}},"devStats":{"dialogs":{"total":200,"correct":188},"responses":{"total":2358,"correct":2346}}},{"index":10400,"runtimeInSeconds":11459.441,"objectiveValue":-6.152475131837956,"trainingStats":{"dialogs":{"total":200,"correct":198},"responses":{"total":2434,"correct":2432}},"devStats":{"dialogs":{"total":200,"correct":191},"responses":{"total":2358,"correct":2349}}},{"index":10600,"runtimeInSeconds":11675.281,"objectiveValue":-2.3086348990064636,"trainingStats":{"dialogs":{"total":200,"correct":200},"responses":{"total":2434,"correct":2434}},"devStats":{"dialogs":{"total":200,"correct":196},"responses":{"total":2358,"correct":2354}}},{"index":10800,"runtimeInSeconds":11891.046,"objectiveValue":-2.0836196738769566,"trainingStats":{"dialogs":{"total":200,"correct":200},"responses":{"total":2434,"correct":2434}},"devStats":{"dialogs":{"total":200,"correct":195},"responses":{"total":2358,"correct":2353}}},{"index":11000,"runtimeInSeconds":12109.216,"objectiveValue":-1.6785448924185271,"trainingStats":{"dialogs":{"total":200,"correct":200},"responses":{"total":2434,"correct":2434}},"devStats":{"dialogs":{"total":200,"correct":195},"responses":{"total":2358,"correct":2353}}},{"index":11200,"runtimeInSeconds":12325.447,"objectiveValue":-0.7699052256692656,"trainingStats":{"dialogs":{"total":200,"correct":199},"responses":{"total":2434,"correct":2433}},"devStats":{"dialogs":{"total":200,"correct":199},"responses":{"total":2358,"correct":2357}}},{"index":11400,"runtimeInSeconds":12543.347,"objectiveValue":-1.012617113069543,"trainingStats":{"dialogs":{"total":200,"correct":200},"responses":{"total":2434,"correct":2434}},"devStats":{"dialogs":{"total":200,"correct":194},"responses":{"total":2358,"correct":2352}}},{"index":11600,"runtimeInSeconds":12762.687,"objectiveValue":-1.0294438332269584,"trainingStats":{"dialogs":{"total":200,"correct":200},"responses":{"total":2434,"correct":2434}},"devStats":{"dialogs":{"total":200,"correct":198},"responses":{"total":2358,"correct":2356}}},{"index":11800,"runtimeInSeconds":12979.162,"objectiveValue":-1.0215218197063096,"trainingStats":{"dialogs":{"total":200,"correct":199},"responses":{"total":2434,"correct":2433}},"devStats":{"dialogs":{"total":200,"correct":197},"responses":{"total":2358,"correct":2355}}},{"index":12000,"runtimeInSeconds":13196.217,"objectiveValue":-1.0933636816408514,"trainingStats":{"dialogs":{"total":200,"correct":200},"responses":{"total":2434,"correct":2434}},"devStats":{"dialogs":{"total":200,"correct":195},"responses":{"total":2358,"correct":2353}}},{"index":12200,"runtimeInSeconds":13415.756,"objectiveValue":-0.6698050666674042,"trainingStats":{"dialogs":{"total":200,"correct":200},"responses":{"total":2434,"correct":2434}},"devStats":{"dialogs":{"total":200,"correct":197},"responses":{"total":2358,"correct":2355}}},{"index":12400,"runtimeInSeconds":13630.524,"objectiveValue":-1.426572266621792,"trainingStats":{"dialogs":{"total":200,"correct":200},"responses":{"total":2434,"correct":2434}},"devStats":{"dialogs":{"total":200,"correct":198},"responses":{"total":2358,"correct":2356}}},{"index":12600,"runtimeInSeconds":13845.313,"objectiveValue":-1.7001216825945253,"trainingStats":{"dialogs":{"total":200,"correct":200},"responses":{"total":2434,"correct":2434}},"devStats":{"dialogs":{"total":200,"correct":196},"responses":{"total":2358,"correct":2354}}},{"index":12800,"runtimeInSeconds":14060.377,"objectiveValue":-0.4787359671283361,"trainingStats":{"dialogs":{"total":200,"correct":200},"responses":{"total":2434,"correct":2434}},"devStats":{"dialogs":{"total":200,"correct":195},"responses":{"total":2358,"correct":2353}}},{"index":13000,"runtimeInSeconds":14276.091,"objectiveValue":-0.5184772273998011,"trainingStats":{"dialogs":{"total":200,"correct":200},"responses":{"total":2434,"correct":2434}},"devStats":{"dialogs":{"total":200,"correct":194},"responses":{"total":2358,"correct":2352}}},{"index":13200,"runtimeInSeconds":14491.237,"objectiveValue":-0.6743839024614885,"trainingStats":{"dialogs":{"total":200,"correct":200},"responses":{"total":2434,"correct":2434}},"devStats":{"dialogs":{"total":200,"correct":197},"responses":{"total":2358,"correct":2355}}},{"index":13400,"runtimeInSeconds":14703.565,"objectiveValue":-0.3534298949414652,"trainingStats":{"dialogs":{"total":200,"correct":200},"responses":{"total":2434,"correct":2434}},"devStats":{"dialogs":{"total":200,"correct":197},"responses":{"total":2358,"correct":2355}}},{"index":13600,"runtimeInSeconds":14918.511,"objectiveValue":-0.5827330921655677,"trainingStats":{"dialogs":{"total":200,"correct":200},"responses":{"total":2434,"correct":2434}},"devStats":{"dialogs":{"total":200,"correct":199},"responses":{"total":2358,"correct":2357}}},{"index":13800,"runtimeInSeconds":15134.93,"objectiveValue":-0.19042100373028145,"trainingStats":{"dialogs":{"total":200,"correct":200},"responses":{"total":2434,"correct":2434}},"devStats":{"dialogs":{"total":200,"correct":195},"responses":{"total":2358,"correct":2353}}},{"index":14000,"runtimeInSeconds":15352.03,"objectiveValue":-0.11760657325977902,"trainingStats":{"dialogs":{"total":200,"correct":200},"responses":{"total":2434,"correct":2434}},"devStats":{"dialogs":{"total":200,"correct":198},"responses":{"total":2358,"correct":2356}}},{"index":14200,"runtimeInSeconds":15570.424,"objectiveValue":-0.237551030786762,"trainingStats":{"dialogs":{"total":200,"correct":200},"responses":{"total":2434,"correct":2434}},"devStats":{"dialogs":{"total":200,"correct":197},"responses":{"total":2358,"correct":2355}}},{"index":14400,"runtimeInSeconds":15786.875,"objectiveValue":-55.42318273711702,"trainingStats":{"dialogs":{"total":200,"correct":191},"responses":{"total":2434,"correct":2425}},"devStats":{"dialogs":{"total":200,"correct":172},"responses":{"total":2358,"correct":2330}}},{"index":14600,"runtimeInSeconds":16003.076,"objectiveValue":-19.90494238905042,"trainingStats":{"dialogs":{"total":200,"correct":195},"responses":{"total":2434,"correct":2429}},"devStats":{"dialogs":{"total":200,"correct":185},"responses":{"total":2358,"correct":2343}}},{"index":14800,"runtimeInSeconds":16221.536,"objectiveValue":-25.08128471185911,"trainingStats":{"dialogs":{"total":200,"correct":195},"responses":{"total":2434,"correct":2429}},"devStats":{"dialogs":{"total":200,"correct":188},"responses":{"total":2358,"correct":2346}}},{"index":15000,"runtimeInSeconds":16440.124,"objectiveValue":-3.4313705506387424,"trainingStats":{"dialogs":{"total":200,"correct":198},"responses":{"total":2434,"correct":2432}},"devStats":{"dialogs":{"total":200,"correct":190},"responses":{"total":2358,"correct":2348}}},{"index":15200,"runtimeInSeconds":16657.369,"objectiveValue":-2.558710731246645,"trainingStats":{"dialogs":{"total":200,"correct":200},"responses":{"total":2434,"correct":2434}},"devStats":{"dialogs":{"total":200,"correct":191},"responses":{"total":2358,"correct":2349}}},{"index":15400,"runtimeInSeconds":16877.017,"objectiveValue":-5.8638530898001,"trainingStats":{"dialogs":{"total":200,"correct":199},"responses":{"total":2434,"correct":2433}},"devStats":{"dialogs":{"total":200,"correct":191},"responses":{"total":2358,"correct":2349}}},{"index":15600,"runtimeInSeconds":17092.629,"objectiveValue":-3.1418383097490143,"trainingStats":{"dialogs":{"total":200,"correct":199},"responses":{"total":2434,"correct":2433}},"devStats":{"dialogs":{"total":200,"correct":190},"responses":{"total":2358,"correct":2348}}},{"index":15800,"runtimeInSeconds":17310.626,"objectiveValue":-3.2455898000272487,"trainingStats":{"dialogs":{"total":200,"correct":198},"responses":{"total":2434,"correct":2432}},"devStats":{"dialogs":{"total":200,"correct":191},"responses":{"total":2358,"correct":2349}}},{"index":16000,"runtimeInSeconds":17526.772,"objectiveValue":-3.3549994224081794,"trainingStats":{"dialogs":{"total":200,"correct":200},"responses":{"total":2434,"correct":2434}},"devStats":{"dialogs":{"total":200,"correct":192},"responses":{"total":2358,"correct":2350}}},{"index":16200,"runtimeInSeconds":17743.957,"objectiveValue":-3.770154177788269,"trainingStats":{"dialogs":{"total":200,"correct":198},"responses":{"total":2434,"correct":2432}},"devStats":{"dialogs":{"total":200,"correct":189},"responses":{"total":2358,"correct":2347}}},{"index":16400,"runtimeInSeconds":17962.077,"objectiveValue":-3.396974417579316,"trainingStats":{"dialogs":{"total":200,"correct":200},"responses":{"total":2434,"correct":2434}},"devStats":{"dialogs":{"total":200,"correct":196},"responses":{"total":2358,"correct":2354}}},{"index":16600,"runtimeInSeconds":18181.064,"objectiveValue":-2.5967808603228515,"trainingStats":{"dialogs":{"total":200,"correct":200},"responses":{"total":2434,"correct":2434}},"devStats":{"dialogs":{"total":200,"correct":192},"responses":{"total":2358,"correct":2350}}},{"index":16800,"runtimeInSeconds":18400.237,"objectiveValue":-1.5892124472621239,"trainingStats":{"dialogs":{"total":200,"correct":200},"responses":{"total":2434,"correct":2434}},"devStats":{"dialogs":{"total":200,"correct":194},"responses":{"total":2358,"correct":2352}}},{"index":17000,"runtimeInSeconds":18616.974,"objectiveValue":-1.1927630547323047,"trainingStats":{"dialogs":{"total":200,"correct":199},"responses":{"total":2434,"correct":2433}},"devStats":{"dialogs":{"total":200,"correct":193},"responses":{"total":2358,"correct":2351}}},{"index":17200,"runtimeInSeconds":18833.583,"objectiveValue":-1.6403144200227064,"trainingStats":{"dialogs":{"total":200,"correct":200},"responses":{"total":2434,"correct":2434}},"devStats":{"dialogs":{"total":200,"correct":191},"responses":{"total":2358,"correct":2349}}},{"index":17400,"runtimeInSeconds":19052.593,"objectiveValue":-0.8866196259887321,"trainingStats":{"dialogs":{"total":200,"correct":200},"responses":{"total":2434,"correct":2434}},"devStats":{"dialogs":{"total":200,"correct":197},"responses":{"total":2358,"correct":2355}}},{"index":17600,"runtimeInSeconds":19272.744,"objectiveValue":-0.9348193865442593,"trainingStats":{"dialogs":{"total":200,"correct":200},"responses":{"total":2434,"correct":2434}},"devStats":{"dialogs":{"total":200,"correct":196},"responses":{"total":2358,"correct":2354}}},{"index":17800,"runtimeInSeconds":19489.238,"objectiveValue":-1.2320754847049282,"trainingStats":{"dialogs":{"total":200,"correct":198},"responses":{"total":2434,"correct":2432}},"devStats":{"dialogs":{"total":200,"correct":190},"responses":{"total":2358,"correct":2348}}},{"index":18000,"runtimeInSeconds":19707.751,"objectiveValue":-1.5345354805995481,"trainingStats":{"dialogs":{"total":200,"correct":200},"responses":{"total":2434,"correct":2434}},"devStats":{"dialogs":{"total":200,"correct":194},"responses":{"total":2358,"correct":2352}}},{"index":18200,"runtimeInSeconds":19923.243,"objectiveValue":-0.47255994541181595,"trainingStats":{"dialogs":{"total":200,"correct":200},"responses":{"total":2434,"correct":2434}},"devStats":{"dialogs":{"total":200,"correct":195},"responses":{"total":2358,"correct":2353}}},{"index":18400,"runtimeInSeconds":20140.03,"objectiveValue":-1.6034366793970078,"trainingStats":{"dialogs":{"total":200,"correct":200},"responses":{"total":2434,"correct":2434}},"devStats":{"dialogs":{"total":200,"correct":193},"responses":{"total":2358,"correct":2351}}},{"index":18600,"runtimeInSeconds":20355.679,"objectiveValue":-0.5082093633817073,"trainingStats":{"dialogs":{"total":200,"correct":200},"responses":{"total":2434,"correct":2434}},"devStats":{"dialogs":{"total":200,"correct":194},"responses":{"total":2358,"correct":2352}}},{"index":18800,"runtimeInSeconds":20570.669,"objectiveValue":-0.5029418954556931,"trainingStats":{"dialogs":{"total":200,"correct":200},"responses":{"total":2434,"correct":2434}},"devStats":{"dialogs":{"total":200,"correct":194},"responses":{"total":2358,"correct":2352}}},{"index":19000,"runtimeInSeconds":20788.516,"objectiveValue":-0.577053788903745,"trainingStats":{"dialogs":{"total":200,"correct":200},"responses":{"total":2434,"correct":2434}},"devStats":{"dialogs":{"total":200,"correct":193},"responses":{"total":2358,"correct":2351}}},{"index":19200,"runtimeInSeconds":21004.845,"objectiveValue":-0.2892351879473573,"trainingStats":{"dialogs":{"total":200,"correct":200},"responses":{"total":2434,"correct":2434}},"devStats":{"dialogs":{"total":200,"correct":195},"responses":{"total":2358,"correct":2353}}},{"index":19400,"runtimeInSeconds":21219.353,"objectiveValue":-0.3312501105607015,"trainingStats":{"dialogs":{"total":200,"correct":200},"responses":{"total":2434,"correct":2434}},"devStats":{"dialogs":{"total":200,"correct":193},"responses":{"total":2358,"correct":2351}}},{"index":19600,"runtimeInSeconds":21436.357,"objectiveValue":-0.26968236605903106,"trainingStats":{"dialogs":{"total":200,"correct":200},"responses":{"total":2434,"correct":2434}},"devStats":{"dialogs":{"total":200,"correct":198},"responses":{"total":2358,"correct":2356}}},{"index":19800,"runtimeInSeconds":21650.898,"objectiveValue":-0.45025982852768437,"trainingStats":{"dialogs":{"total":200,"correct":200},"responses":{"total":2434,"correct":2434}},"devStats":{"dialogs":{"total":200,"correct":196},"responses":{"total":2358,"correct":2354}}},{"index":20000,"runtimeInSeconds":21869.7,"objectiveValue":-0.06997456051392643,"trainingStats":{"dialogs":{"total":200,"correct":200},"responses":{"total":2434,"correct":2434}},"devStats":{"dialogs":{"total":200,"correct":196},"responses":{"total":2358,"correct":2354}}},{"index":20200,"runtimeInSeconds":22083.761,"objectiveValue":-0.11218110576916551,"trainingStats":{"dialogs":{"total":200,"correct":200},"responses":{"total":2434,"correct":2434}},"devStats":{"dialogs":{"total":200,"correct":196},"responses":{"total":2358,"correct":2354}}},{"index":20400,"runtimeInSeconds":22301.34,"objectiveValue":-0.2555471371093476,"trainingStats":{"dialogs":{"total":200,"correct":200},"responses":{"total":2434,"correct":2434}},"devStats":{"dialogs":{"total":200,"correct":195},"responses":{"total":2358,"correct":2353}}},{"index":20600,"runtimeInSeconds":22518.795,"objectiveValue":-0.16188115793403146,"trainingStats":{"dialogs":{"total":200,"correct":199},"responses":{"total":2434,"correct":2433}},"devStats":{"dialogs":{"total":200,"correct":197},"responses":{"total":2358,"correct":2355}}},{"index":20800,"runtimeInSeconds":22734.14,"objectiveValue":-0.20663570269239157,"trainingStats":{"dialogs":{"total":200,"correct":200},"responses":{"total":2434,"correct":2434}},"devStats":{"dialogs":{"total":200,"correct":198},"responses":{"total":2358,"correct":2356}}},{"index":21000,"runtimeInSeconds":22951.359,"objectiveValue":-0.1302481839251379,"trainingStats":{"dialogs":{"total":200,"correct":200},"responses":{"total":2434,"correct":2434}},"devStats":{"dialogs":{"total":200,"correct":194},"responses":{"total":2358,"correct":2352}}},{"index":21200,"runtimeInSeconds":23169.001,"objectiveValue":-0.1030754394133259,"trainingStats":{"dialogs":{"total":200,"correct":200},"responses":{"total":2434,"correct":2434}},"devStats":{"dialogs":{"total":200,"correct":196},"responses":{"total":2358,"correct":2354}}},{"index":21400,"runtimeInSeconds":23386.022,"objectiveValue":-0.18182404945243752,"trainingStats":{"dialogs":{"total":200,"correct":200},"responses":{"total":2434,"correct":2434}},"devStats":{"dialogs":{"total":200,"correct":197},"responses":{"total":2358,"correct":2355}}},{"index":21600,"runtimeInSeconds":23599.835,"objectiveValue":-0.07426203807538599,"trainingStats":{"dialogs":{"total":200,"correct":200},"responses":{"total":2434,"correct":2434}},"devStats":{"dialogs":{"total":200,"correct":196},"responses":{"total":2358,"correct":2354}}},{"index":21800,"runtimeInSeconds":23818.733,"objectiveValue":-0.10390763682190673,"trainingStats":{"dialogs":{"total":200,"correct":200},"responses":{"total":2434,"correct":2434}},"devStats":{"dialogs":{"total":200,"correct":198},"responses":{"total":2358,"correct":2356}}},{"index":22000,"runtimeInSeconds":24034.863,"objectiveValue":-0.07442929500734641,"trainingStats":{"dialogs":{"total":200,"correct":200},"responses":{"total":2434,"correct":2434}},"devStats":{"dialogs":{"total":200,"correct":195},"responses":{"total":2358,"correct":2353}}},{"index":22200,"runtimeInSeconds":24252.029,"objectiveValue":-0.11058746435726946,"trainingStats":{"dialogs":{"total":200,"correct":200},"responses":{"total":2434,"correct":2434}},"devStats":{"dialogs":{"total":200,"correct":195},"responses":{"total":2358,"correct":2353}}},{"index":22400,"runtimeInSeconds":24470.579,"objectiveValue":-0.09441547714097477,"trainingStats":{"dialogs":{"total":200,"correct":200},"responses":{"total":2434,"correct":2434}},"devStats":{"dialogs":{"total":200,"correct":197},"responses":{"total":2358,"correct":2355}}},{"index":22600,"runtimeInSeconds":24686.621,"objectiveValue":-0.06909075322861685,"trainingStats":{"dialogs":{"total":200,"correct":200},"responses":{"total":2434,"correct":2434}},"devStats":{"dialogs":{"total":200,"correct":196},"responses":{"total":2358,"correct":2354}}},{"index":22800,"runtimeInSeconds":24903.246,"objectiveValue":-0.07766073133629542,"trainingStats":{"dialogs":{"total":200,"correct":200},"responses":{"total":2434,"correct":2434}},"devStats":{"dialogs":{"total":200,"correct":199},"responses":{"total":2358,"correct":2357}}},{"index":23000,"runtimeInSeconds":25121.161,"objectiveValue":-0.05915262432588486,"trainingStats":{"dialogs":{"total":200,"correct":200},"responses":{"total":2434,"correct":2434}},"devStats":{"dialogs":{"total":200,"correct":198},"responses":{"total":2358,"correct":2356}}},{"index":23200,"runtimeInSeconds":25337.796,"objectiveValue":-0.02374710497711456,"trainingStats":{"dialogs":{"total":200,"correct":200},"responses":{"total":2434,"correct":2434}},"devStats":{"dialogs":{"total":200,"correct":197},"responses":{"total":2358,"correct":2355}}},{"index":23400,"runtimeInSeconds":25558.617,"objectiveValue":-0.01670451895914806,"trainingStats":{"dialogs":{"total":200,"correct":200},"responses":{"total":2434,"correct":2434}},"devStats":{"dialogs":{"total":200,"correct":196},"responses":{"total":2358,"correct":2354}}},{"index":23600,"runtimeInSeconds":25777.09,"objectiveValue":-0.03342968200080018,"trainingStats":{"dialogs":{"total":200,"correct":200},"responses":{"total":2434,"correct":2434}},"devStats":{"dialogs":{"total":200,"correct":196},"responses":{"total":2358,"correct":2354}}},{"index":23800,"runtimeInSeconds":25993.154,"objectiveValue":-0.043720767735463954,"trainingStats":{"dialogs":{"total":200,"correct":200},"responses":{"total":2434,"correct":2434}},"devStats":{"dialogs":{"total":200,"correct":199},"responses":{"total":2358,"correct":2357}}},{"index":24000,"runtimeInSeconds":26210.512,"objectiveValue":-0.05732968194672144,"trainingStats":{"dialogs":{"total":200,"correct":200},"responses":{"total":2434,"correct":2434}},"devStats":{"dialogs":{"total":200,"correct":199},"responses":{"total":2358,"correct":2357}}},{"index":24200,"runtimeInSeconds":26427.217,"objectiveValue":-0.05416673568661949,"trainingStats":{"dialogs":{"total":200,"correct":200},"responses":{"total":2434,"correct":2434}},"devStats":{"dialogs":{"total":200,"correct":193},"responses":{"total":2358,"correct":2351}}},{"index":24400,"runtimeInSeconds":26645.873,"objectiveValue":-0.018810578282715876,"trainingStats":{"dialogs":{"total":200,"correct":200},"responses":{"total":2434,"correct":2434}},"devStats":{"dialogs":{"total":200,"correct":197},"responses":{"total":2358,"correct":2355}}},{"index":24600,"runtimeInSeconds":26864.036,"objectiveValue":-0.013906472298793798,"trainingStats":{"dialogs":{"total":200,"correct":200},"responses":{"total":2434,"correct":2434}},"devStats":{"dialogs":{"total":200,"correct":198},"responses":{"total":2358,"correct":2356}}},{"index":24800,"runtimeInSeconds":27084.198,"objectiveValue":-0.045916776007281744,"trainingStats":{"dialogs":{"total":200,"correct":200},"responses":{"total":2434,"correct":2434}},"devStats":{"dialogs":{"total":200,"correct":196},"responses":{"total":2358,"correct":2354}}},{"index":25000,"runtimeInSeconds":27301.493,"objectiveValue":-0.01372055736716551,"trainingStats":{"dialogs":{"total":200,"correct":200},"responses":{"total":2434,"correct":2434}},"devStats":{"dialogs":{"total":200,"correct":198},"responses":{"total":2358,"correct":2356}}},{"index":25200,"runtimeInSeconds":27516.674,"objectiveValue":-0.0056967778885836234,"trainingStats":{"dialogs":{"total":200,"correct":200},"responses":{"total":2434,"correct":2434}},"devStats":{"dialogs":{"total":200,"correct":197},"responses":{"total":2358,"correct":2355}}},{"index":25400,"runtimeInSeconds":27733.15,"objectiveValue":-0.008325141184611907,"trainingStats":{"dialogs":{"total":200,"correct":200},"responses":{"total":2434,"correct":2434}},"devStats":{"dialogs":{"total":200,"correct":197},"responses":{"total":2358,"correct":2355}}},{"index":25600,"runtimeInSeconds":27952.033,"objectiveValue":-0.0062419798219687924,"trainingStats":{"dialogs":{"total":200,"correct":200},"responses":{"total":2434,"correct":2434}},"devStats":{"dialogs":{"total":200,"correct":197},"responses":{"total":2358,"correct":2355}}},{"index":25800,"runtimeInSeconds":28166.72,"objectiveValue":-0.010129065132638945,"trainingStats":{"dialogs":{"total":200,"correct":200},"responses":{"total":2434,"correct":2434}},"devStats":{"dialogs":{"total":200,"correct":197},"responses":{"total":2358,"correct":2355}}},{"index":26000,"runtimeInSeconds":28385.623,"objectiveValue":-11.68587980041857,"trainingStats":{"dialogs":{"total":200,"correct":173},"responses":{"total":2434,"correct":2404}},"devStats":{"dialogs":{"total":200,"correct":154},"responses":{"total":2358,"correct":2307}}},{"index":26200,"runtimeInSeconds":28602.582,"objectiveValue":-1.4297991339047456,"trainingStats":{"dialogs":{"total":200,"correct":195},"responses":{"total":2434,"correct":2428}},"devStats":{"dialogs":{"total":200,"correct":190},"responses":{"total":2358,"correct":2348}}},{"index":26400,"runtimeInSeconds":28814.881,"objectiveValue":-1.0518476322760273,"trainingStats":{"dialogs":{"total":200,"correct":200},"responses":{"total":2434,"correct":2434}},"devStats":{"dialogs":{"total":200,"correct":196},"responses":{"total":2358,"correct":2354}}},{"index":26600,"runtimeInSeconds":29031.535,"objectiveValue":-0.8759088622509227,"trainingStats":{"dialogs":{"total":200,"correct":200},"responses":{"total":2434,"correct":2434}},"devStats":{"dialogs":{"total":200,"correct":195},"responses":{"total":2358,"correct":2353}}},{"index":26800,"runtimeInSeconds":29246.947,"objectiveValue":-0.640004692098596,"trainingStats":{"dialogs":{"total":200,"correct":200},"responses":{"total":2434,"correct":2434}},"devStats":{"dialogs":{"total":200,"correct":197},"responses":{"total":2358,"correct":2355}}},{"index":27000,"runtimeInSeconds":29462.642,"objectiveValue":-1.450578074676923,"trainingStats":{"dialogs":{"total":200,"correct":200},"responses":{"total":2434,"correct":2434}},"devStats":{"dialogs":{"total":200,"correct":195},"responses":{"total":2358,"correct":2353}}},{"index":27200,"runtimeInSeconds":29678.448,"objectiveValue":-2.3248711220471505,"trainingStats":{"dialogs":{"total":200,"correct":200},"responses":{"total":2434,"correct":2434}},"devStats":{"dialogs":{"total":200,"correct":196},"responses":{"total":2358,"correct":2354}}},{"index":27400,"runtimeInSeconds":29897.736,"objectiveValue":-0.3747796673289778,"trainingStats":{"dialogs":{"total":200,"correct":200},"responses":{"total":2434,"correct":2434}},"devStats":{"dialogs":{"total":200,"correct":197},"responses":{"total":2358,"correct":2355}}},{"index":27600,"runtimeInSeconds":30114.682,"objectiveValue":-3.390251147980291,"trainingStats":{"dialogs":{"total":200,"correct":199},"responses":{"total":2434,"correct":2433}},"devStats":{"dialogs":{"total":200,"correct":195},"responses":{"total":2358,"correct":2353}}},{"index":27800,"runtimeInSeconds":30333.002,"objectiveValue":-0.2660702780610525,"trainingStats":{"dialogs":{"total":200,"correct":200},"responses":{"total":2434,"correct":2434}},"devStats":{"dialogs":{"total":200,"correct":198},"responses":{"total":2358,"correct":2356}}},{"index":28000,"runtimeInSeconds":30546.271,"objectiveValue":-0.762309806555596,"trainingStats":{"dialogs":{"total":200,"correct":200},"responses":{"total":2434,"correct":2434}},"devStats":{"dialogs":{"total":200,"correct":196},"responses":{"total":2358,"correct":2354}}},{"index":28200,"runtimeInSeconds":30763.196,"objectiveValue":-0.10998883885204074,"trainingStats":{"dialogs":{"total":200,"correct":200},"responses":{"total":2434,"correct":2434}},"devStats":{"dialogs":{"total":200,"correct":197},"responses":{"total":2358,"correct":2355}}},{"index":28400,"runtimeInSeconds":30978.796,"objectiveValue":-0.6382565298537366,"trainingStats":{"dialogs":{"total":200,"correct":200},"responses":{"total":2434,"correct":2434}},"devStats":{"dialogs":{"total":200,"correct":197},"responses":{"total":2358,"correct":2355}}},{"index":28600,"runtimeInSeconds":31195.244,"objectiveValue":-0.6493354164152653,"trainingStats":{"dialogs":{"total":200,"correct":200},"responses":{"total":2434,"correct":2434}},"devStats":{"dialogs":{"total":200,"correct":193},"responses":{"total":2358,"correct":2351}}},{"index":28800,"runtimeInSeconds":31412.855,"objectiveValue":-0.6810075386608668,"trainingStats":{"dialogs":{"total":200,"correct":200},"responses":{"total":2434,"correct":2434}},"devStats":{"dialogs":{"total":200,"correct":197},"responses":{"total":2358,"correct":2355}}},{"index":29000,"runtimeInSeconds":31628.758,"objectiveValue":-0.6588911543982008,"trainingStats":{"dialogs":{"total":200,"correct":200},"responses":{"total":2434,"correct":2434}},"devStats":{"dialogs":{"total":200,"correct":200},"responses":{"total":2358,"correct":2358}}},{"index":29200,"runtimeInSeconds":31845.187,"objectiveValue":-0.19315089177358452,"trainingStats":{"dialogs":{"total":200,"correct":200},"responses":{"total":2434,"correct":2434}},"devStats":{"dialogs":{"total":200,"correct":194},"responses":{"total":2358,"correct":2352}}},{"index":29400,"runtimeInSeconds":32061.588,"objectiveValue":-1.1563001998677178,"trainingStats":{"dialogs":{"total":200,"correct":200},"responses":{"total":2434,"correct":2434}},"devStats":{"dialogs":{"total":200,"correct":198},"responses":{"total":2358,"correct":2356}}},{"index":29600,"runtimeInSeconds":32276.346,"objectiveValue":-1.1050916139371103,"trainingStats":{"dialogs":{"total":200,"correct":200},"responses":{"total":2434,"correct":2434}},"devStats":{"dialogs":{"total":200,"correct":195},"responses":{"total":2358,"correct":2353}}},{"index":29800,"runtimeInSeconds":32490.622,"objectiveValue":-1.0215676688112478,"trainingStats":{"dialogs":{"total":200,"correct":199},"responses":{"total":2434,"correct":2433}},"devStats":{"dialogs":{"total":200,"correct":198},"responses":{"total":2358,"correct":2356}}},{"index":30000,"runtimeInSeconds":32709.814,"objectiveValue":-0.26143219049684335,"trainingStats":{"dialogs":{"total":200,"correct":200},"responses":{"total":2434,"correct":2434}},"devStats":{"dialogs":{"total":200,"correct":199},"responses":{"total":2358,"correct":2357}}},{"index":30200,"runtimeInSeconds":32930.3,"objectiveValue":-0.33011254564443054,"trainingStats":{"dialogs":{"total":200,"correct":200},"responses":{"total":2434,"correct":2434}},"devStats":{"dialogs":{"total":200,"correct":198},"responses":{"total":2358,"correct":2356}}},{"index":30400,"runtimeInSeconds":33146.608,"objectiveValue":-0.2083980788404736,"trainingStats":{"dialogs":{"total":200,"correct":200},"responses":{"total":2434,"correct":2434}},"devStats":{"dialogs":{"total":200,"correct":198},"responses":{"total":2358,"correct":2356}}},{"index":30600,"runtimeInSeconds":33362.278,"objectiveValue":-0.13711551641660794,"trainingStats":{"dialogs":{"total":200,"correct":200},"responses":{"total":2434,"correct":2434}},"devStats":{"dialogs":{"total":200,"correct":199},"responses":{"total":2358,"correct":2357}}},{"index":30800,"runtimeInSeconds":33582.314,"objectiveValue":-0.13503015531010154,"trainingStats":{"dialogs":{"total":200,"correct":200},"responses":{"total":2434,"correct":2434}},"devStats":{"dialogs":{"total":200,"correct":198},"responses":{"total":2358,"correct":2356}}},{"index":31000,"runtimeInSeconds":33801.839,"objectiveValue":-0.07110185763937196,"trainingStats":{"dialogs":{"total":200,"correct":200},"responses":{"total":2434,"correct":2434}},"devStats":{"dialogs":{"total":200,"correct":198},"responses":{"total":2358,"correct":2356}}},{"index":31200,"runtimeInSeconds":34024.474,"objectiveValue":-0.051363936529746725,"trainingStats":{"dialogs":{"total":200,"correct":200},"responses":{"total":2434,"correct":2434}},"devStats":{"dialogs":{"total":200,"correct":199},"responses":{"total":2358,"correct":2357}}},{"index":31400,"runtimeInSeconds":34243.395,"objectiveValue":-0.11574669290647542,"trainingStats":{"dialogs":{"total":200,"correct":200},"responses":{"total":2434,"correct":2434}},"devStats":{"dialogs":{"total":200,"correct":200},"responses":{"total":2358,"correct":2358}}},{"index":31600,"runtimeInSeconds":34461.27,"objectiveValue":-0.0766541401163668,"trainingStats":{"dialogs":{"total":200,"correct":200},"responses":{"total":2434,"correct":2434}},"devStats":{"dialogs":{"total":200,"correct":199},"responses":{"total":2358,"correct":2357}}},{"index":31800,"runtimeInSeconds":34676.357,"objectiveValue":-0.11460040460502599,"trainingStats":{"dialogs":{"total":200,"correct":200},"responses":{"total":2434,"correct":2434}},"devStats":{"dialogs":{"total":200,"correct":199},"responses":{"total":2358,"correct":2357}}},{"index":32000,"runtimeInSeconds":34894.399,"objectiveValue":-0.04325290429612055,"trainingStats":{"dialogs":{"total":200,"correct":200},"responses":{"total":2434,"correct":2434}},"devStats":{"dialogs":{"total":200,"correct":199},"responses":{"total":2358,"correct":2357}}},{"index":32200,"runtimeInSeconds":35110.645,"objectiveValue":-0.2104830585212463,"trainingStats":{"dialogs":{"total":200,"correct":200},"responses":{"total":2434,"correct":2434}},"devStats":{"dialogs":{"total":200,"correct":199},"responses":{"total":2358,"correct":2357}}},{"index":32400,"runtimeInSeconds":35327.445,"objectiveValue":-0.1668525093042875,"trainingStats":{"dialogs":{"total":200,"correct":200},"responses":{"total":2434,"correct":2434}},"devStats":{"dialogs":{"total":200,"correct":198},"responses":{"total":2358,"correct":2356}}},{"index":32600,"runtimeInSeconds":35544.255,"objectiveValue":-0.18326166224663262,"trainingStats":{"dialogs":{"total":200,"correct":200},"responses":{"total":2434,"correct":2434}},"devStats":{"dialogs":{"total":200,"correct":199},"responses":{"total":2358,"correct":2357}}},{"index":32800,"runtimeInSeconds":35759.967,"objectiveValue":-0.09563705600967337,"trainingStats":{"dialogs":{"total":200,"correct":200},"responses":{"total":2434,"correct":2434}},"devStats":{"dialogs":{"total":200,"correct":199},"responses":{"total":2358,"correct":2357}}},{"index":33000,"runtimeInSeconds":35978.022,"objectiveValue":-0.08669804136023325,"trainingStats":{"dialogs":{"total":200,"correct":200},"responses":{"total":2434,"correct":2434}},"devStats":{"dialogs":{"total":200,"correct":198},"responses":{"total":2358,"correct":2356}}},{"index":33200,"runtimeInSeconds":36196.429,"objectiveValue":-0.03454016725510501,"trainingStats":{"dialogs":{"total":200,"correct":200},"responses":{"total":2434,"correct":2434}},"devStats":{"dialogs":{"total":200,"correct":199},"responses":{"total":2358,"correct":2357}}},{"index":33400,"runtimeInSeconds":36411.116,"objectiveValue":-0.021002011832082404,"trainingStats":{"dialogs":{"total":200,"correct":200},"responses":{"total":2434,"correct":2434}},"devStats":{"dialogs":{"total":200,"correct":198},"responses":{"total":2358,"correct":2356}}},{"index":33600,"runtimeInSeconds":36624.942,"objectiveValue":-0.11651936401382332,"trainingStats":{"dialogs":{"total":200,"correct":200},"responses":{"total":2434,"correct":2434}},"devStats":{"dialogs":{"total":200,"correct":199},"responses":{"total":2358,"correct":2357}}},{"index":33800,"runtimeInSeconds":36843.233,"objectiveValue":-0.04259271468369594,"trainingStats":{"dialogs":{"total":200,"correct":200},"responses":{"total":2434,"correct":2434}},"devStats":{"dialogs":{"total":200,"correct":200},"responses":{"total":2358,"correct":2358}}},{"index":34000,"runtimeInSeconds":37061.814,"objectiveValue":-0.05609808800052848,"trainingStats":{"dialogs":{"total":200,"correct":200},"responses":{"total":2434,"correct":2434}},"devStats":{"dialogs":{"total":200,"correct":197},"responses":{"total":2358,"correct":2355}}},{"index":34200,"runtimeInSeconds":37282.737,"objectiveValue":-0.07305323115761708,"trainingStats":{"dialogs":{"total":200,"correct":200},"responses":{"total":2434,"correct":2434}},"devStats":{"dialogs":{"total":200,"correct":199},"responses":{"total":2358,"correct":2357}}},{"index":34400,"runtimeInSeconds":37502.741,"objectiveValue":-0.03779008520069005,"trainingStats":{"dialogs":{"total":200,"correct":200},"responses":{"total":2434,"correct":2434}},"devStats":{"dialogs":{"total":200,"correct":198},"responses":{"total":2358,"correct":2356}}},{"index":34600,"runtimeInSeconds":37722.083,"objectiveValue":-0.03851339198622289,"trainingStats":{"dialogs":{"total":200,"correct":200},"responses":{"total":2434,"correct":2434}},"devStats":{"dialogs":{"total":200,"correct":200},"responses":{"total":2358,"correct":2358}}},{"index":34800,"runtimeInSeconds":37940.841,"objectiveValue":-0.01551047528013579,"trainingStats":{"dialogs":{"total":200,"correct":200},"responses":{"total":2434,"correct":2434}},"devStats":{"dialogs":{"total":200,"correct":198},"responses":{"total":2358,"correct":2356}}},{"index":35000,"runtimeInSeconds":38158.867,"objectiveValue":-0.042432338022765144,"trainingStats":{"dialogs":{"total":200,"correct":200},"responses":{"total":2434,"correct":2434}},"devStats":{"dialogs":{"total":200,"correct":200},"responses":{"total":2358,"correct":2358}}},{"index":35200,"runtimeInSeconds":38374.872,"objectiveValue":-0.01621864510484749,"trainingStats":{"dialogs":{"total":200,"correct":200},"responses":{"total":2434,"correct":2434}},"devStats":{"dialogs":{"total":200,"correct":200},"responses":{"total":2358,"correct":2358}}},{"index":35400,"runtimeInSeconds":38592.945,"objectiveValue":-0.031999738732588066,"trainingStats":{"dialogs":{"total":200,"correct":200},"responses":{"total":2434,"correct":2434}},"devStats":{"dialogs":{"total":200,"correct":199},"responses":{"total":2358,"correct":2357}}},{"index":35600,"runtimeInSeconds":38818.839,"objectiveValue":-0.026440526075710465,"trainingStats":{"dialogs":{"total":200,"correct":200},"responses":{"total":2434,"correct":2434}},"devStats":{"dialogs":{"total":200,"correct":199},"responses":{"total":2358,"correct":2357}}},{"index":35800,"runtimeInSeconds":39036.737,"objectiveValue":-0.01581659645710092,"trainingStats":{"dialogs":{"total":200,"correct":200},"responses":{"total":2434,"correct":2434}},"devStats":{"dialogs":{"total":200,"correct":200},"responses":{"total":2358,"correct":2358}}},{"index":36000,"runtimeInSeconds":39253.123,"objectiveValue":-0.04501180693238693,"trainingStats":{"dialogs":{"total":200,"correct":200},"responses":{"total":2434,"correct":2434}},"devStats":{"dialogs":{"total":200,"correct":200},"responses":{"total":2358,"correct":2358}}},{"index":36200,"runtimeInSeconds":39471.008,"objectiveValue":-0.01882633281701766,"trainingStats":{"dialogs":{"total":200,"correct":200},"responses":{"total":2434,"correct":2434}},"devStats":{"dialogs":{"total":200,"correct":200},"responses":{"total":2358,"correct":2358}}},{"index":36400,"runtimeInSeconds":39694.585,"objectiveValue":-0.042051003527403714,"trainingStats":{"dialogs":{"total":200,"correct":200},"responses":{"total":2434,"correct":2434}},"devStats":{"dialogs":{"total":200,"correct":200},"responses":{"total":2358,"correct":2358}}},{"index":36600,"runtimeInSeconds":39913.898,"objectiveValue":-0.012140329804363945,"trainingStats":{"dialogs":{"total":200,"correct":200},"responses":{"total":2434,"correct":2434}},"devStats":{"dialogs":{"total":200,"correct":199},"responses":{"total":2358,"correct":2357}}},{"index":36800,"runtimeInSeconds":40134.316,"objectiveValue":-0.009847615716637713,"trainingStats":{"dialogs":{"total":200,"correct":200},"responses":{"total":2434,"correct":2434}},"devStats":{"dialogs":{"total":200,"correct":199},"responses":{"total":2358,"correct":2357}}},{"index":37000,"runtimeInSeconds":40353.22,"objectiveValue":-0.004446819187707639,"trainingStats":{"dialogs":{"total":200,"correct":200},"responses":{"total":2434,"correct":2434}},"devStats":{"dialogs":{"total":200,"correct":199},"responses":{"total":2358,"correct":2357}}},{"index":37200,"runtimeInSeconds":40572.742,"objectiveValue":-0.008407495542248448,"trainingStats":{"dialogs":{"total":200,"correct":200},"responses":{"total":2434,"correct":2434}},"devStats":{"dialogs":{"total":200,"correct":199},"responses":{"total":2358,"correct":2357}}},{"index":37400,"runtimeInSeconds":40790.932,"objectiveValue":-0.01003195930485672,"trainingStats":{"dialogs":{"total":200,"correct":200},"responses":{"total":2434,"correct":2434}},"devStats":{"dialogs":{"total":200,"correct":200},"responses":{"total":2358,"correct":2358}}},{"index":37600,"runtimeInSeconds":41011.803,"objectiveValue":-0.013606524699528104,"trainingStats":{"dialogs":{"total":200,"correct":200},"responses":{"total":2434,"correct":2434}},"devStats":{"dialogs":{"total":200,"correct":200},"responses":{"total":2358,"correct":2358}}},{"index":37800,"runtimeInSeconds":41230.508,"objectiveValue":-0.0059792143742998394,"trainingStats":{"dialogs":{"total":200,"correct":200},"responses":{"total":2434,"correct":2434}},"devStats":{"dialogs":{"total":200,"correct":200},"responses":{"total":2358,"correct":2358}}},{"index":38000,"runtimeInSeconds":41449.731,"objectiveValue":-0.0048133664273865805,"trainingStats":{"dialogs":{"total":200,"correct":200},"responses":{"total":2434,"correct":2434}},"devStats":{"dialogs":{"total":200,"correct":199},"responses":{"total":2358,"correct":2357}}},{"index":38200,"runtimeInSeconds":41668.142,"objectiveValue":-0.02828143598849358,"trainingStats":{"dialogs":{"total":200,"correct":200},"responses":{"total":2434,"correct":2434}},"devStats":{"dialogs":{"total":200,"correct":200},"responses":{"total":2358,"correct":2358}}},{"index":38400,"runtimeInSeconds":41886.967,"objectiveValue":-0.004126783396741979,"trainingStats":{"dialogs":{"total":200,"correct":200},"responses":{"total":2434,"correct":2434}},"devStats":{"dialogs":{"total":200,"correct":200},"responses":{"total":2358,"correct":2358}}},{"index":38600,"runtimeInSeconds":42105.422,"objectiveValue":-0.010399035236273902,"trainingStats":{"dialogs":{"total":200,"correct":200},"responses":{"total":2434,"correct":2434}},"devStats":{"dialogs":{"total":200,"correct":200},"responses":{"total":2358,"correct":2358}}},{"index":38800,"runtimeInSeconds":42326.006,"objectiveValue":-0.002907350250235484,"trainingStats":{"dialogs":{"total":200,"correct":200},"responses":{"total":2434,"correct":2434}},"devStats":{"dialogs":{"total":200,"correct":200},"responses":{"total":2358,"correct":2358}}},{"index":39000,"runtimeInSeconds":42542.499,"objectiveValue":-0.0041737194388299335,"trainingStats":{"dialogs":{"total":200,"correct":200},"responses":{"total":2434,"correct":2434}},"devStats":{"dialogs":{"total":200,"correct":200},"responses":{"total":2358,"correct":2358}}},{"index":39200,"runtimeInSeconds":42762.883,"objectiveValue":-0.012853453327342303,"trainingStats":{"dialogs":{"total":200,"correct":200},"responses":{"total":2434,"correct":2434}},"devStats":{"dialogs":{"total":200,"correct":200},"responses":{"total":2358,"correct":2358}}},{"index":39400,"runtimeInSeconds":42979.85,"objectiveValue":-0.004091220797456741,"trainingStats":{"dialogs":{"total":200,"correct":200},"responses":{"total":2434,"correct":2434}},"devStats":{"dialogs":{"total":200,"correct":199},"responses":{"total":2358,"correct":2357}}},{"index":39600,"runtimeInSeconds":43197.976,"objectiveValue":-0.0035192272596332344,"trainingStats":{"dialogs":{"total":200,"correct":200},"responses":{"total":2434,"correct":2434}},"devStats":{"dialogs":{"total":200,"correct":200},"responses":{"total":2358,"correct":2358}}},{"index":39800,"runtimeInSeconds":43417.523,"objectiveValue":-0.0023729033755181587,"trainingStats":{"dialogs":{"total":200,"correct":200},"responses":{"total":2434,"correct":2434}},"devStats":{"dialogs":{"total":200,"correct":199},"responses":{"total":2358,"correct":2357}}},{"index":40000,"runtimeInSeconds":43640.307,"objectiveValue":-0.0025594196023845293,"trainingStats":{"dialogs":{"total":200,"correct":200},"responses":{"total":2434,"correct":2434}},"devStats":{"dialogs":{"total":200,"correct":200},"responses":{"total":2358,"correct":2358}}},{"index":40200,"runtimeInSeconds":43861.957,"objectiveValue":-0.0030959350686835243,"trainingStats":{"dialogs":{"total":200,"correct":200},"responses":{"total":2434,"correct":2434}},"devStats":{"dialogs":{"total":200,"correct":200},"responses":{"total":2358,"correct":2358}}},{"index":40400,"runtimeInSeconds":44084.363,"objectiveValue":-0.008109428309858516,"trainingStats":{"dialogs":{"total":200,"correct":200},"responses":{"total":2434,"correct":2434}},"devStats":{"dialogs":{"total":200,"correct":199},"responses":{"total":2358,"correct":2357}}},{"index":40600,"runtimeInSeconds":44306.18,"objectiveValue":-0.003152536501771922,"trainingStats":{"dialogs":{"total":200,"correct":200},"responses":{"total":2434,"correct":2434}},"devStats":{"dialogs":{"total":200,"correct":200},"responses":{"total":2358,"correct":2358}}},{"index":40800,"runtimeInSeconds":44528.776,"objectiveValue":-0.0012009599921928287,"trainingStats":{"dialogs":{"total":200,"correct":200},"responses":{"total":2434,"correct":2434}},"devStats":{"dialogs":{"total":200,"correct":200},"responses":{"total":2358,"correct":2358}}},{"index":41000,"runtimeInSeconds":44750.505,"objectiveValue":-0.0013742874195312358,"trainingStats":{"dialogs":{"total":200,"correct":200},"responses":{"total":2434,"correct":2434}},"devStats":{"dialogs":{"total":200,"correct":200},"responses":{"total":2358,"correct":2358}}},{"index":41200,"runtimeInSeconds":44965.598,"objectiveValue":-0.002794443130938998,"trainingStats":{"dialogs":{"total":200,"correct":200},"responses":{"total":2434,"correct":2434}},"devStats":{"dialogs":{"total":200,"correct":199},"responses":{"total":2358,"correct":2357}}},{"index":41400,"runtimeInSeconds":45186.482,"objectiveValue":-0.004902231633030869,"trainingStats":{"dialogs":{"total":200,"correct":200},"responses":{"total":2434,"correct":2434}},"devStats":{"dialogs":{"total":200,"correct":200},"responses":{"total":2358,"correct":2358}}},{"index":41600,"runtimeInSeconds":45406.422,"objectiveValue":-0.001330381001807324,"trainingStats":{"dialogs":{"total":200,"correct":200},"responses":{"total":2434,"correct":2434}},"devStats":{"dialogs":{"total":200,"correct":200},"responses":{"total":2358,"correct":2358}}},{"index":41800,"runtimeInSeconds":45627.674,"objectiveValue":-0.0018696492549059199,"trainingStats":{"dialogs":{"total":200,"correct":200},"responses":{"total":2434,"correct":2434}},"devStats":{"dialogs":{"total":200,"correct":200},"responses":{"total":2358,"correct":2358}}},{"index":42000,"runtimeInSeconds":45845.994,"objectiveValue":-0.001115399156619425,"trainingStats":{"dialogs":{"total":200,"correct":200},"responses":{"total":2434,"correct":2434}},"devStats":{"dialogs":{"total":200,"correct":200},"responses":{"total":2358,"correct":2358}}},{"index":42200,"runtimeInSeconds":46066.303,"objectiveValue":-0.002202416675525429,"trainingStats":{"dialogs":{"total":200,"correct":200},"responses":{"total":2434,"correct":2434}},"devStats":{"dialogs":{"total":200,"correct":199},"responses":{"total":2358,"correct":2357}}},{"index":42400,"runtimeInSeconds":46290.069,"objectiveValue":-0.0006730243057354913,"trainingStats":{"dialogs":{"total":200,"correct":200},"responses":{"total":2434,"correct":2434}},"devStats":{"dialogs":{"total":200,"correct":200},"responses":{"total":2358,"correct":2358}}},{"index":42600,"runtimeInSeconds":46508.304,"objectiveValue":-0.0010164701666122613,"trainingStats":{"dialogs":{"total":200,"correct":200},"responses":{"total":2434,"correct":2434}},"devStats":{"dialogs":{"total":200,"correct":200},"responses":{"total":2358,"correct":2358}}},{"index":42800,"runtimeInSeconds":46730.07,"objectiveValue":-0.0009369709815248142,"trainingStats":{"dialogs":{"total":200,"correct":200},"responses":{"total":2434,"correct":2434}},"devStats":{"dialogs":{"total":200,"correct":200},"responses":{"total":2358,"correct":2358}}},{"index":43000,"runtimeInSeconds":46948.004,"objectiveValue":-0.0004937316831096544,"trainingStats":{"dialogs":{"total":200,"correct":200},"responses":{"total":2434,"correct":2434}},"devStats":{"dialogs":{"total":200,"correct":199},"responses":{"total":2358,"correct":2357}}},{"index":43200,"runtimeInSeconds":47170.903,"objectiveValue":-0.0008367953547851881,"trainingStats":{"dialogs":{"total":200,"correct":200},"responses":{"total":2434,"correct":2434}},"devStats":{"dialogs":{"total":200,"correct":200},"responses":{"total":2358,"correct":2358}}},{"index":43400,"runtimeInSeconds":47392.958,"objectiveValue":-0.0006774123515861212,"trainingStats":{"dialogs":{"total":200,"correct":200},"responses":{"total":2434,"correct":2434}},"devStats":{"dialogs":{"total":200,"correct":200},"responses":{"total":2358,"correct":2358}}},{"index":43600,"runtimeInSeconds":47612.488,"objectiveValue":-0.00023365552603655385,"trainingStats":{"dialogs":{"total":200,"correct":200},"responses":{"total":2434,"correct":2434}},"devStats":{"dialogs":{"total":200,"correct":200},"responses":{"total":2358,"correct":2358}}},{"index":43800,"runtimeInSeconds":47833.499,"objectiveValue":-0.0002026044807582254,"trainingStats":{"dialogs":{"total":200,"correct":200},"responses":{"total":2434,"correct":2434}},"devStats":{"dialogs":{"total":200,"correct":200},"responses":{"total":2358,"correct":2358}}},{"index":44000,"runtimeInSeconds":48051.451,"objectiveValue":-0.0005262929154080036,"trainingStats":{"dialogs":{"total":200,"correct":200},"responses":{"total":2434,"correct":2434}},"devStats":{"dialogs":{"total":200,"correct":200},"responses":{"total":2358,"correct":2358}}},{"index":44200,"runtimeInSeconds":48274.747,"objectiveValue":-0.00033692236551577327,"trainingStats":{"dialogs":{"total":200,"correct":200},"responses":{"total":2434,"correct":2434}},"devStats":{"dialogs":{"total":200,"correct":200},"responses":{"total":2358,"correct":2358}}},{"index":44400,"runtimeInSeconds":48491.166,"objectiveValue":-0.0005291866914529378,"trainingStats":{"dialogs":{"total":200,"correct":200},"responses":{"total":2434,"correct":2434}},"devStats":{"dialogs":{"total":200,"correct":200},"responses":{"total":2358,"correct":2358}}},{"index":44600,"runtimeInSeconds":48709.957,"objectiveValue":-0.0004605326571454758,"trainingStats":{"dialogs":{"total":200,"correct":200},"responses":{"total":2434,"correct":2434}},"devStats":{"dialogs":{"total":200,"correct":200},"responses":{"total":2358,"correct":2358}}},{"index":44800,"runtimeInSeconds":48930.256,"objectiveValue":-0.00011781343048484798,"trainingStats":{"dialogs":{"total":200,"correct":200},"responses":{"total":2434,"correct":2434}},"devStats":{"dialogs":{"total":200,"correct":200},"responses":{"total":2358,"correct":2358}}},{"index":45000,"runtimeInSeconds":49149.113,"objectiveValue":-0.00069552203808314,"trainingStats":{"dialogs":{"total":200,"correct":200},"responses":{"total":2434,"correct":2434}},"devStats":{"dialogs":{"total":200,"correct":200},"responses":{"total":2358,"correct":2358}}},{"index":45200,"runtimeInSeconds":49371.652,"objectiveValue":-0.0004842375567267305,"trainingStats":{"dialogs":{"total":200,"correct":200},"responses":{"total":2434,"correct":2434}},"devStats":{"dialogs":{"total":200,"correct":200},"responses":{"total":2358,"correct":2358}}},{"index":45400,"runtimeInSeconds":49593.337,"objectiveValue":-0.0005522060755850107,"trainingStats":{"dialogs":{"total":200,"correct":200},"responses":{"total":2434,"correct":2434}},"devStats":{"dialogs":{"total":200,"correct":200},"responses":{"total":2358,"correct":2358}}},{"index":45600,"runtimeInSeconds":49813.484,"objectiveValue":-0.00019784889366429183,"trainingStats":{"dialogs":{"total":200,"correct":200},"responses":{"total":2434,"correct":2434}},"devStats":{"dialogs":{"total":200,"correct":200},"responses":{"total":2358,"correct":2358}}},{"index":45800,"runtimeInSeconds":50032.94,"objectiveValue":-0.00006393862921371689,"trainingStats":{"dialogs":{"total":200,"correct":200},"responses":{"total":2434,"correct":2434}},"devStats":{"dialogs":{"total":200,"correct":200},"responses":{"total":2358,"correct":2358}}},{"index":46000,"runtimeInSeconds":50255.211,"objectiveValue":-0.00011956959551569415,"trainingStats":{"dialogs":{"total":200,"correct":200},"responses":{"total":2434,"correct":2434}},"devStats":{"dialogs":{"total":200,"correct":200},"responses":{"total":2358,"correct":2358}}},{"index":46200,"runtimeInSeconds":50473.492,"objectiveValue":-1534.2061859808748,"trainingStats":{"dialogs":{"total":200,"correct":158},"responses":{"total":2434,"correct":2391}},"devStats":{"dialogs":{"total":200,"correct":141},"responses":{"total":2358,"correct":2296}}},{"index":46400,"runtimeInSeconds":50693.23,"objectiveValue":-1.7289022834179237,"trainingStats":{"dialogs":{"total":200,"correct":197},"responses":{"total":2434,"correct":2431}},"devStats":{"dialogs":{"total":200,"correct":188},"responses":{"total":2358,"correct":2346}}},{"index":46600,"runtimeInSeconds":50911.92,"objectiveValue":-0.06665293226039398,"trainingStats":{"dialogs":{"total":200,"correct":200},"responses":{"total":2434,"correct":2434}},"devStats":{"dialogs":{"total":200,"correct":192},"responses":{"total":2358,"correct":2350}}},{"index":46800,"runtimeInSeconds":51132.563,"objectiveValue":-0.3482441289636844,"trainingStats":{"dialogs":{"total":200,"correct":198},"responses":{"total":2434,"correct":2432}},"devStats":{"dialogs":{"total":200,"correct":195},"responses":{"total":2358,"correct":2353}}},{"index":47000,"runtimeInSeconds":51355.353,"objectiveValue":-0.391541990678761,"trainingStats":{"dialogs":{"total":200,"correct":200},"responses":{"total":2434,"correct":2434}},"devStats":{"dialogs":{"total":200,"correct":194},"responses":{"total":2358,"correct":2352}}},{"index":47200,"runtimeInSeconds":51576.718,"objectiveValue":-0.17205557817683326,"trainingStats":{"dialogs":{"total":200,"correct":200},"responses":{"total":2434,"correct":2434}},"devStats":{"dialogs":{"total":200,"correct":198},"responses":{"total":2358,"correct":2356}}},{"index":47400,"runtimeInSeconds":51794.454,"objectiveValue":-0.8870501136030461,"trainingStats":{"dialogs":{"total":200,"correct":200},"responses":{"total":2434,"correct":2434}},"devStats":{"dialogs":{"total":200,"correct":196},"responses":{"total":2358,"correct":2354}}},{"index":47600,"runtimeInSeconds":52015.093,"objectiveValue":-0.29273415437431766,"trainingStats":{"dialogs":{"total":200,"correct":200},"responses":{"total":2434,"correct":2434}},"devStats":{"dialogs":{"total":200,"correct":195},"responses":{"total":2358,"correct":2353}}},{"index":47800,"runtimeInSeconds":52237.587,"objectiveValue":-0.07013511798628283,"trainingStats":{"dialogs":{"total":200,"correct":200},"responses":{"total":2434,"correct":2434}},"devStats":{"dialogs":{"total":200,"correct":195},"responses":{"total":2358,"correct":2353}}},{"index":48000,"runtimeInSeconds":52456.405,"objectiveValue":-0.06729787235958282,"trainingStats":{"dialogs":{"total":200,"correct":200},"responses":{"total":2434,"correct":2434}},"devStats":{"dialogs":{"total":200,"correct":194},"responses":{"total":2358,"correct":2352}}},{"index":48200,"runtimeInSeconds":52677.893,"objectiveValue":-0.06558245813326201,"trainingStats":{"dialogs":{"total":200,"correct":200},"responses":{"total":2434,"correct":2434}},"devStats":{"dialogs":{"total":200,"correct":197},"responses":{"total":2358,"correct":2355}}},{"index":48400,"runtimeInSeconds":52899.104,"objectiveValue":-0.09774502768484473,"trainingStats":{"dialogs":{"total":200,"correct":200},"responses":{"total":2434,"correct":2434}},"devStats":{"dialogs":{"total":200,"correct":197},"responses":{"total":2358,"correct":2355}}},{"index":48600,"runtimeInSeconds":53117.836,"objectiveValue":-0.08485393463709111,"trainingStats":{"dialogs":{"total":200,"correct":200},"responses":{"total":2434,"correct":2434}},"devStats":{"dialogs":{"total":200,"correct":198},"responses":{"total":2358,"correct":2356}}},{"index":48800,"runtimeInSeconds":53338.218,"objectiveValue":-0.05699536581988227,"trainingStats":{"dialogs":{"total":200,"correct":200},"responses":{"total":2434,"correct":2434}},"devStats":{"dialogs":{"total":200,"correct":196},"responses":{"total":2358,"correct":2354}}},{"index":49000,"runtimeInSeconds":53559.981,"objectiveValue":-0.22815350495193806,"trainingStats":{"dialogs":{"total":200,"correct":200},"responses":{"total":2434,"correct":2434}},"devStats":{"dialogs":{"total":200,"correct":198},"responses":{"total":2358,"correct":2356}}},{"index":49200,"runtimeInSeconds":53777.464,"objectiveValue":-0.034560173013172574,"trainingStats":{"dialogs":{"total":200,"correct":200},"responses":{"total":2434,"correct":2434}},"devStats":{"dialogs":{"total":200,"correct":195},"responses":{"total":2358,"correct":2353}}},{"index":49400,"runtimeInSeconds":54000.981,"objectiveValue":-0.04580485607163974,"trainingStats":{"dialogs":{"total":200,"correct":200},"responses":{"total":2434,"correct":2434}},"devStats":{"dialogs":{"total":200,"correct":196},"responses":{"total":2358,"correct":2354}}},{"index":49600,"runtimeInSeconds":54219.869,"objectiveValue":-0.2635077369114121,"trainingStats":{"dialogs":{"total":200,"correct":200},"responses":{"total":2434,"correct":2434}},"devStats":{"dialogs":{"total":200,"correct":196},"responses":{"total":2358,"correct":2354}}},{"index":49800,"runtimeInSeconds":54436.675,"objectiveValue":-0.049563223210536106,"trainingStats":{"dialogs":{"total":200,"correct":200},"responses":{"total":2434,"correct":2434}},"devStats":{"dialogs":{"total":200,"correct":194},"responses":{"total":2358,"correct":2352}}},{"index":50000,"runtimeInSeconds":54654.856,"objectiveValue":-0.042411432197500216,"trainingStats":{"dialogs":{"total":200,"correct":200},"responses":{"total":2434,"correct":2434}},"devStats":{"dialogs":{"total":200,"correct":198},"responses":{"total":2358,"correct":2356}}},{"index":50200,"runtimeInSeconds":54874.575,"objectiveValue":-0.09189306704084212,"trainingStats":{"dialogs":{"total":200,"correct":200},"responses":{"total":2434,"correct":2434}},"devStats":{"dialogs":{"total":200,"correct":198},"responses":{"total":2358,"correct":2356}}},{"index":50400,"runtimeInSeconds":55102.255,"objectiveValue":-0.0876112067341557,"trainingStats":{"dialogs":{"total":200,"correct":200},"responses":{"total":2434,"correct":2434}},"devStats":{"dialogs":{"total":200,"correct":195},"responses":{"total":2358,"correct":2353}}},{"index":50600,"runtimeInSeconds":55327.835,"objectiveValue":-0.053620978916649596,"trainingStats":{"dialogs":{"total":200,"correct":200},"responses":{"total":2434,"correct":2434}},"devStats":{"dialogs":{"total":200,"correct":195},"responses":{"total":2358,"correct":2353}}},{"index":50800,"runtimeInSeconds":55547.577,"objectiveValue":-0.10673429202418694,"trainingStats":{"dialogs":{"total":200,"correct":200},"responses":{"total":2434,"correct":2434}},"devStats":{"dialogs":{"total":200,"correct":198},"responses":{"total":2358,"correct":2356}}},{"index":51000,"runtimeInSeconds":55766.309,"objectiveValue":-0.008926902817230473,"trainingStats":{"dialogs":{"total":200,"correct":200},"responses":{"total":2434,"correct":2434}},"devStats":{"dialogs":{"total":200,"correct":197},"responses":{"total":2358,"correct":2355}}},{"index":51200,"runtimeInSeconds":55985.046,"objectiveValue":-0.04562796165857095,"trainingStats":{"dialogs":{"total":200,"correct":200},"responses":{"total":2434,"correct":2434}},"devStats":{"dialogs":{"total":200,"correct":194},"responses":{"total":2358,"correct":2352}}},{"index":51400,"runtimeInSeconds":56204.244,"objectiveValue":-0.05904876356511052,"trainingStats":{"dialogs":{"total":200,"correct":200},"responses":{"total":2434,"correct":2434}},"devStats":{"dialogs":{"total":200,"correct":196},"responses":{"total":2358,"correct":2354}}},{"index":51600,"runtimeInSeconds":56423.942,"objectiveValue":-0.01889087591317934,"trainingStats":{"dialogs":{"total":200,"correct":200},"responses":{"total":2434,"correct":2434}},"devStats":{"dialogs":{"total":200,"correct":198},"responses":{"total":2358,"correct":2356}}},{"index":51800,"runtimeInSeconds":56644.591,"objectiveValue":-0.022444864298137877,"trainingStats":{"dialogs":{"total":200,"correct":200},"responses":{"total":2434,"correct":2434}},"devStats":{"dialogs":{"total":200,"correct":197},"responses":{"total":2358,"correct":2355}}},{"index":52000,"runtimeInSeconds":56866.996,"objectiveValue":-0.03372348439467876,"trainingStats":{"dialogs":{"total":200,"correct":200},"responses":{"total":2434,"correct":2434}},"devStats":{"dialogs":{"total":200,"correct":195},"responses":{"total":2358,"correct":2353}}},{"index":52200,"runtimeInSeconds":57086.526,"objectiveValue":-0.003320735996215773,"trainingStats":{"dialogs":{"total":200,"correct":200},"responses":{"total":2434,"correct":2434}},"devStats":{"dialogs":{"total":200,"correct":199},"responses":{"total":2358,"correct":2357}}},{"index":52400,"runtimeInSeconds":57309.625,"objectiveValue":-0.04603952241073926,"trainingStats":{"dialogs":{"total":200,"correct":200},"responses":{"total":2434,"correct":2434}},"devStats":{"dialogs":{"total":200,"correct":198},"responses":{"total":2358,"correct":2356}}},{"index":52600,"runtimeInSeconds":57528.498,"objectiveValue":-0.03537114904507276,"trainingStats":{"dialogs":{"total":200,"correct":200},"responses":{"total":2434,"correct":2434}},"devStats":{"dialogs":{"total":200,"correct":195},"responses":{"total":2358,"correct":2353}}},{"index":52800,"runtimeInSeconds":57746.288,"objectiveValue":-0.01798941601062689,"trainingStats":{"dialogs":{"total":200,"correct":200},"responses":{"total":2434,"correct":2434}},"devStats":{"dialogs":{"total":200,"correct":197},"responses":{"total":2358,"correct":2355}}},{"index":53000,"runtimeInSeconds":57971.632,"objectiveValue":-0.02027572579206442,"trainingStats":{"dialogs":{"total":200,"correct":200},"responses":{"total":2434,"correct":2434}},"devStats":{"dialogs":{"total":200,"correct":196},"responses":{"total":2358,"correct":2354}}},{"index":53200,"runtimeInSeconds":58192.873,"objectiveValue":-0.025746579569821876,"trainingStats":{"dialogs":{"total":200,"correct":200},"responses":{"total":2434,"correct":2434}},"devStats":{"dialogs":{"total":200,"correct":198},"responses":{"total":2358,"correct":2356}}},{"index":53400,"runtimeInSeconds":58417.438,"objectiveValue":-0.01836722175702185,"trainingStats":{"dialogs":{"total":200,"correct":200},"responses":{"total":2434,"correct":2434}},"devStats":{"dialogs":{"total":200,"correct":196},"responses":{"total":2358,"correct":2354}}},{"index":53600,"runtimeInSeconds":58638.816,"objectiveValue":-0.03374934743857074,"trainingStats":{"dialogs":{"total":200,"correct":200},"responses":{"total":2434,"correct":2434}},"devStats":{"dialogs":{"total":200,"correct":198},"responses":{"total":2358,"correct":2356}}},{"index":53800,"runtimeInSeconds":58860.489,"objectiveValue":-0.0145340351870607,"trainingStats":{"dialogs":{"total":200,"correct":200},"responses":{"total":2434,"correct":2434}},"devStats":{"dialogs":{"total":200,"correct":199},"responses":{"total":2358,"correct":2357}}},{"index":54000,"runtimeInSeconds":59087.259,"objectiveValue":-0.014362955038440582,"trainingStats":{"dialogs":{"total":200,"correct":200},"responses":{"total":2434,"correct":2434}},"devStats":{"dialogs":{"total":200,"correct":198},"responses":{"total":2358,"correct":2356}}},{"index":54200,"runtimeInSeconds":59305.4,"objectiveValue":-0.011259154193806048,"trainingStats":{"dialogs":{"total":200,"correct":200},"responses":{"total":2434,"correct":2434}},"devStats":{"dialogs":{"total":200,"correct":197},"responses":{"total":2358,"correct":2355}}},{"index":54400,"runtimeInSeconds":59524.698,"objectiveValue":-0.020704010812983238,"trainingStats":{"dialogs":{"total":200,"correct":200},"responses":{"total":2434,"correct":2434}},"devStats":{"dialogs":{"total":200,"correct":196},"responses":{"total":2358,"correct":2354}}},{"index":54600,"runtimeInSeconds":59748.678,"objectiveValue":-0.017135701506903498,"trainingStats":{"dialogs":{"total":200,"correct":200},"responses":{"total":2434,"correct":2434}},"devStats":{"dialogs":{"total":200,"correct":199},"responses":{"total":2358,"correct":2357}}},{"index":54800,"runtimeInSeconds":59968.203,"objectiveValue":-0.0073812169025051855,"trainingStats":{"dialogs":{"total":200,"correct":200},"responses":{"total":2434,"correct":2434}},"devStats":{"dialogs":{"total":200,"correct":199},"responses":{"total":2358,"correct":2357}}},{"index":55000,"runtimeInSeconds":60188.023,"objectiveValue":-0.008630726115394099,"trainingStats":{"dialogs":{"total":200,"correct":200},"responses":{"total":2434,"correct":2434}},"devStats":{"dialogs":{"total":200,"correct":197},"responses":{"total":2358,"correct":2355}}},{"index":55200,"runtimeInSeconds":60404.803,"objectiveValue":-0.004750939169134039,"trainingStats":{"dialogs":{"total":200,"correct":200},"responses":{"total":2434,"correct":2434}},"devStats":{"dialogs":{"total":200,"correct":198},"responses":{"total":2358,"correct":2356}}},{"index":55400,"runtimeInSeconds":60620.591,"objectiveValue":-0.001860191895756084,"trainingStats":{"dialogs":{"total":200,"correct":200},"responses":{"total":2434,"correct":2434}},"devStats":{"dialogs":{"total":200,"correct":199},"responses":{"total":2358,"correct":2357}}},{"index":55600,"runtimeInSeconds":60838.882,"objectiveValue":-0.029454657400498616,"trainingStats":{"dialogs":{"total":200,"correct":200},"responses":{"total":2434,"correct":2434}},"devStats":{"dialogs":{"total":200,"correct":199},"responses":{"total":2358,"correct":2357}}},{"index":55800,"runtimeInSeconds":61056.881,"objectiveValue":-0.025144082044268625,"trainingStats":{"dialogs":{"total":200,"correct":200},"responses":{"total":2434,"correct":2434}},"devStats":{"dialogs":{"total":200,"correct":198},"responses":{"total":2358,"correct":2356}}},{"index":56000,"runtimeInSeconds":61277.394,"objectiveValue":-0.01271170016723787,"trainingStats":{"dialogs":{"total":200,"correct":200},"responses":{"total":2434,"correct":2434}},"devStats":{"dialogs":{"total":200,"correct":198},"responses":{"total":2358,"correct":2356}}},{"index":56200,"runtimeInSeconds":61497.493,"objectiveValue":-0.0004503125138535329,"trainingStats":{"dialogs":{"total":200,"correct":200},"responses":{"total":2434,"correct":2434}},"devStats":{"dialogs":{"total":200,"correct":198},"responses":{"total":2358,"correct":2356}}},{"index":56400,"runtimeInSeconds":61717.518,"objectiveValue":-0.017399278524009222,"trainingStats":{"dialogs":{"total":200,"correct":200},"responses":{"total":2434,"correct":2434}},"devStats":{"dialogs":{"total":200,"correct":197},"responses":{"total":2358,"correct":2355}}},{"index":56600,"runtimeInSeconds":61944.4,"objectiveValue":-0.007170906497648993,"trainingStats":{"dialogs":{"total":200,"correct":200},"responses":{"total":2434,"correct":2434}},"devStats":{"dialogs":{"total":200,"correct":197},"responses":{"total":2358,"correct":2355}}},{"index":56800,"runtimeInSeconds":62165.331,"objectiveValue":-0.008459085579331463,"trainingStats":{"dialogs":{"total":200,"correct":200},"responses":{"total":2434,"correct":2434}},"devStats":{"dialogs":{"total":200,"correct":197},"responses":{"total":2358,"correct":2355}}},{"index":57000,"runtimeInSeconds":62384.516,"objectiveValue":-0.008249056082322155,"trainingStats":{"dialogs":{"total":200,"correct":200},"responses":{"total":2434,"correct":2434}},"devStats":{"dialogs":{"total":200,"correct":197},"responses":{"total":2358,"correct":2355}}},{"index":57200,"runtimeInSeconds":62606.573,"objectiveValue":-0.006755801926072881,"trainingStats":{"dialogs":{"total":200,"correct":200},"responses":{"total":2434,"correct":2434}},"devStats":{"dialogs":{"total":200,"correct":198},"responses":{"total":2358,"correct":2356}}},{"index":57400,"runtimeInSeconds":62827.416,"objectiveValue":-0.004337928707858045,"trainingStats":{"dialogs":{"total":200,"correct":200},"responses":{"total":2434,"correct":2434}},"devStats":{"dialogs":{"total":200,"correct":198},"responses":{"total":2358,"correct":2356}}},{"index":57600,"runtimeInSeconds":63046.055,"objectiveValue":-0.004742764627722324,"trainingStats":{"dialogs":{"total":200,"correct":200},"responses":{"total":2434,"correct":2434}},"devStats":{"dialogs":{"total":200,"correct":198},"responses":{"total":2358,"correct":2356}}},{"index":57800,"runtimeInSeconds":63266.23,"objectiveValue":-0.0035091298238151243,"trainingStats":{"dialogs":{"total":200,"correct":200},"responses":{"total":2434,"correct":2434}},"devStats":{"dialogs":{"total":200,"correct":198},"responses":{"total":2358,"correct":2356}}},{"index":58000,"runtimeInSeconds":63487.767,"objectiveValue":-0.0041543747320008885,"trainingStats":{"dialogs":{"total":200,"correct":200},"responses":{"total":2434,"correct":2434}},"devStats":{"dialogs":{"total":200,"correct":198},"responses":{"total":2358,"correct":2356}}},{"index":58200,"runtimeInSeconds":63709.64,"objectiveValue":-0.0011851610096056564,"trainingStats":{"dialogs":{"total":200,"correct":200},"responses":{"total":2434,"correct":2434}},"devStats":{"dialogs":{"total":200,"correct":198},"responses":{"total":2358,"correct":2356}}}]