[{"index":0,"runtimeInSeconds":300.603,"objectiveValue":-279604.3631003233,"trainingStats":{"dialogs":{"total":200,"correct":0},"responses":{"total":2434,"correct":0}},"devStats":{"dialogs":{"total":200,"correct":0},"responses":{"total":2358,"correct":0}}},{"index":200,"runtimeInSeconds":529.101,"objectiveValue":-61991.62562186021,"trainingStats":{"dialogs":{"total":200,"correct":0},"responses":{"total":2434,"correct":412}},"devStats":{"dialogs":{"total":200,"correct":0},"responses":{"total":2358,"correct":401}}},{"index":400,"runtimeInSeconds":750.544,"objectiveValue":-17695.092850541005,"trainingStats":{"dialogs":{"total":200,"correct":0},"responses":{"total":2434,"correct":1224}},"devStats":{"dialogs":{"total":200,"correct":0},"responses":{"total":2358,"correct":1198}}},{"index":600,"runtimeInSeconds":976.583,"objectiveValue":-12699.916210476284,"trainingStats":{"dialogs":{"total":200,"correct":0},"responses":{"total":2434,"correct":1661}},"devStats":{"dialogs":{"total":200,"correct":0},"responses":{"total":2358,"correct":1578}}},{"index":800,"runtimeInSeconds":1200.579,"objectiveValue":-8655.932572635233,"trainingStats":{"dialogs":{"total":200,"correct":0},"responses":{"total":2434,"correct":1816}},"devStats":{"dialogs":{"total":200,"correct":0},"responses":{"total":2358,"correct":1727}}},{"index":1000,"runtimeInSeconds":1422.545,"objectiveValue":-9672.107719113172,"trainingStats":{"dialogs":{"total":200,"correct":0},"responses":{"total":2434,"correct":1902}},"devStats":{"dialogs":{"total":200,"correct":0},"responses":{"total":2358,"correct":1824}}},{"index":1200,"runtimeInSeconds":1645.166,"objectiveValue":-7308.950230768106,"trainingStats":{"dialogs":{"total":200,"correct":0},"responses":{"total":2434,"correct":1928}},"devStats":{"dialogs":{"total":200,"correct":0},"responses":{"total":2358,"correct":1904}}},{"index":1400,"runtimeInSeconds":1867.393,"objectiveValue":-7420.719010090837,"trainingStats":{"dialogs":{"total":200,"correct":0},"responses":{"total":2434,"correct":2014}},"devStats":{"dialogs":{"total":200,"correct":1},"responses":{"total":2358,"correct":1948}}},{"index":1600,"runtimeInSeconds":2090.733,"objectiveValue":-6154.102992873463,"trainingStats":{"dialogs":{"total":200,"correct":2},"responses":{"total":2434,"correct":2058}},"devStats":{"dialogs":{"total":200,"correct":0},"responses":{"total":2358,"correct":1991}}},{"index":1800,"runtimeInSeconds":2313.407,"objectiveValue":-6192.1614976792,"trainingStats":{"dialogs":{"total":200,"correct":1},"responses":{"total":2434,"correct":2072}},"devStats":{"dialogs":{"total":200,"correct":0},"responses":{"total":2358,"correct":1986}}},{"index":2000,"runtimeInSeconds":2534.639,"objectiveValue":-5614.103062625284,"trainingStats":{"dialogs":{"total":200,"correct":0},"responses":{"total":2434,"correct":2110}},"devStats":{"dialogs":{"total":200,"correct":1},"responses":{"total":2358,"correct":2027}}},{"index":2200,"runtimeInSeconds":2758.605,"objectiveValue":-5904.690481063508,"trainingStats":{"dialogs":{"total":200,"correct":0},"responses":{"total":2434,"correct":2090}},"devStats":{"dialogs":{"total":200,"correct":1},"responses":{"total":2358,"correct":2023}}},{"index":2400,"runtimeInSeconds":2980.422,"objectiveValue":-5784.5794194104255,"trainingStats":{"dialogs":{"total":200,"correct":3},"responses":{"total":2434,"correct":2142}},"devStats":{"dialogs":{"total":200,"correct":1},"responses":{"total":2358,"correct":2080}}},{"index":2600,"runtimeInSeconds":3205.691,"objectiveValue":-7314.968597687574,"trainingStats":{"dialogs":{"total":200,"correct":0},"responses":{"total":2434,"correct":2010}},"devStats":{"dialogs":{"total":200,"correct":2},"responses":{"total":2358,"correct":1936}}},{"index":2800,"runtimeInSeconds":3427.349,"objectiveValue":-4757.7496942024545,"trainingStats":{"dialogs":{"total":200,"correct":1},"responses":{"total":2434,"correct":2187}},"devStats":{"dialogs":{"total":200,"correct":2},"responses":{"total":2358,"correct":2104}}},{"index":3000,"runtimeInSeconds":3648.184,"objectiveValue":-3746.514874829965,"trainingStats":{"dialogs":{"total":200,"correct":6},"responses":{"total":2434,"correct":2199}},"devStats":{"dialogs":{"total":200,"correct":0},"responses":{"total":2358,"correct":2112}}},{"index":3200,"runtimeInSeconds":3874.739,"objectiveValue":-3953.9344101539136,"trainingStats":{"dialogs":{"total":200,"correct":2},"responses":{"total":2434,"correct":2171}},"devStats":{"dialogs":{"total":200,"correct":2},"responses":{"total":2358,"correct":2095}}},{"index":3400,"runtimeInSeconds":4098.721,"objectiveValue":-4405.231585912334,"trainingStats":{"dialogs":{"total":200,"correct":3},"responses":{"total":2434,"correct":2187}},"devStats":{"dialogs":{"total":200,"correct":5},"responses":{"total":2358,"correct":2115}}},{"index":3600,"runtimeInSeconds":4324.724,"objectiveValue":-3679.0029000446607,"trainingStats":{"dialogs":{"total":200,"correct":10},"responses":{"total":2434,"correct":2205}},"devStats":{"dialogs":{"total":200,"correct":11},"responses":{"total":2358,"correct":2134}}},{"index":3800,"runtimeInSeconds":4547.122,"objectiveValue":-3759.338813113974,"trainingStats":{"dialogs":{"total":200,"correct":8},"responses":{"total":2434,"correct":2195}},"devStats":{"dialogs":{"total":200,"correct":5},"responses":{"total":2358,"correct":2114}}},{"index":4000,"runtimeInSeconds":4767.529,"objectiveValue":-3045.4732581825383,"trainingStats":{"dialogs":{"total":200,"correct":11},"responses":{"total":2434,"correct":2204}},"devStats":{"dialogs":{"total":200,"correct":13},"responses":{"total":2358,"correct":2125}}},{"index":4200,"runtimeInSeconds":4990.394,"objectiveValue":-3455.070335530148,"trainingStats":{"dialogs":{"total":200,"correct":13},"responses":{"total":2434,"correct":2203}},"devStats":{"dialogs":{"total":200,"correct":6},"responses":{"total":2358,"correct":2120}}},{"index":4400,"runtimeInSeconds":5210.602,"objectiveValue":-2464.8030190707477,"trainingStats":{"dialogs":{"total":200,"correct":17},"responses":{"total":2434,"correct":2192}},"devStats":{"dialogs":{"total":200,"correct":16},"responses":{"total":2358,"correct":2113}}},{"index":4600,"runtimeInSeconds":5433.15,"objectiveValue":-2226.289051942545,"trainingStats":{"dialogs":{"total":200,"correct":26},"responses":{"total":2434,"correct":2231}},"devStats":{"dialogs":{"total":200,"correct":17},"responses":{"total":2358,"correct":2156}}},{"index":4800,"runtimeInSeconds":5655.833,"objectiveValue":-3475.5539881137856,"trainingStats":{"dialogs":{"total":200,"correct":25},"responses":{"total":2434,"correct":2202}},"devStats":{"dialogs":{"total":200,"correct":9},"responses":{"total":2358,"correct":2103}}},{"index":5000,"runtimeInSeconds":5879.845,"objectiveValue":-2121.462391898745,"trainingStats":{"dialogs":{"total":200,"correct":39},"responses":{"total":2434,"correct":2252}},"devStats":{"dialogs":{"total":200,"correct":22},"responses":{"total":2358,"correct":2149}}},{"index":5200,"runtimeInSeconds":6104.663,"objectiveValue":-1542.9018056897671,"trainingStats":{"dialogs":{"total":200,"correct":47},"responses":{"total":2434,"correct":2253}},"devStats":{"dialogs":{"total":200,"correct":39},"responses":{"total":2358,"correct":2170}}},{"index":5400,"runtimeInSeconds":6330.657,"objectiveValue":-1549.6485342421713,"trainingStats":{"dialogs":{"total":200,"correct":52},"responses":{"total":2434,"correct":2268}},"devStats":{"dialogs":{"total":200,"correct":51},"responses":{"total":2358,"correct":2186}}},{"index":5600,"runtimeInSeconds":6553.464,"objectiveValue":-1055.3983364907756,"trainingStats":{"dialogs":{"total":200,"correct":64},"responses":{"total":2434,"correct":2272}},"devStats":{"dialogs":{"total":200,"correct":42},"responses":{"total":2358,"correct":2163}}},{"index":5800,"runtimeInSeconds":6777.253,"objectiveValue":-1604.5110562253296,"trainingStats":{"dialogs":{"total":200,"correct":64},"responses":{"total":2434,"correct":2274}},"devStats":{"dialogs":{"total":200,"correct":46},"responses":{"total":2358,"correct":2165}}},{"index":6000,"runtimeInSeconds":7002.208,"objectiveValue":-897.1700015507104,"trainingStats":{"dialogs":{"total":200,"correct":86},"responses":{"total":2434,"correct":2303}},"devStats":{"dialogs":{"total":200,"correct":70},"responses":{"total":2358,"correct":2211}}},{"index":6200,"runtimeInSeconds":7227.127,"objectiveValue":-804.1379932206856,"trainingStats":{"dialogs":{"total":200,"correct":85},"responses":{"total":2434,"correct":2297}},"devStats":{"dialogs":{"total":200,"correct":69},"responses":{"total":2358,"correct":2203}}},{"index":6400,"runtimeInSeconds":7449.172,"objectiveValue":-608.599946523637,"trainingStats":{"dialogs":{"total":200,"correct":115},"responses":{"total":2434,"correct":2340}},"devStats":{"dialogs":{"total":200,"correct":84},"responses":{"total":2358,"correct":2230}}},{"index":6600,"runtimeInSeconds":7675.075,"objectiveValue":-908.8608922575567,"trainingStats":{"dialogs":{"total":200,"correct":102},"responses":{"total":2434,"correct":2327}},"devStats":{"dialogs":{"total":200,"correct":83},"responses":{"total":2358,"correct":2225}}},{"index":6800,"runtimeInSeconds":7896.505,"objectiveValue":-386.8977247083371,"trainingStats":{"dialogs":{"total":200,"correct":73},"responses":{"total":2434,"correct":2287}},"devStats":{"dialogs":{"total":200,"correct":63},"responses":{"total":2358,"correct":2186}}},{"index":7000,"runtimeInSeconds":8119.265,"objectiveValue":-754.6444501951875,"trainingStats":{"dialogs":{"total":200,"correct":109},"responses":{"total":2434,"correct":2333}},"devStats":{"dialogs":{"total":200,"correct":83},"responses":{"total":2358,"correct":2221}}},{"index":7200,"runtimeInSeconds":8342.922,"objectiveValue":-353.4382345346189,"trainingStats":{"dialogs":{"total":200,"correct":133},"responses":{"total":2434,"correct":2362}},"devStats":{"dialogs":{"total":200,"correct":100},"responses":{"total":2358,"correct":2253}}},{"index":7400,"runtimeInSeconds":8566.406,"objectiveValue":-382.31561325673675,"trainingStats":{"dialogs":{"total":200,"correct":127},"responses":{"total":2434,"correct":2353}},"devStats":{"dialogs":{"total":200,"correct":105},"responses":{"total":2358,"correct":2255}}},{"index":7600,"runtimeInSeconds":8788.871,"objectiveValue":-287.1165316588844,"trainingStats":{"dialogs":{"total":200,"correct":152},"responses":{"total":2434,"correct":2384}},"devStats":{"dialogs":{"total":200,"correct":118},"responses":{"total":2358,"correct":2271}}},{"index":7800,"runtimeInSeconds":9012.176,"objectiveValue":-341.110925396381,"trainingStats":{"dialogs":{"total":200,"correct":155},"responses":{"total":2434,"correct":2387}},"devStats":{"dialogs":{"total":200,"correct":130},"responses":{"total":2358,"correct":2284}}},{"index":8000,"runtimeInSeconds":9236.296,"objectiveValue":-169.5523103639263,"trainingStats":{"dialogs":{"total":200,"correct":164},"responses":{"total":2434,"correct":2398}},"devStats":{"dialogs":{"total":200,"correct":135},"responses":{"total":2358,"correct":2291}}},{"index":8200,"runtimeInSeconds":9460.384,"objectiveValue":-1118.324222287795,"trainingStats":{"dialogs":{"total":200,"correct":138},"responses":{"total":2434,"correct":2368}},"devStats":{"dialogs":{"total":200,"correct":132},"responses":{"total":2358,"correct":2285}}},{"index":8400,"runtimeInSeconds":9681.484,"objectiveValue":-116.63555837109023,"trainingStats":{"dialogs":{"total":200,"correct":173},"responses":{"total":2434,"correct":2405}},"devStats":{"dialogs":{"total":200,"correct":136},"responses":{"total":2358,"correct":2292}}},{"index":8600,"runtimeInSeconds":9901.73,"objectiveValue":-168.38879901173604,"trainingStats":{"dialogs":{"total":200,"correct":161},"responses":{"total":2434,"correct":2393}},"devStats":{"dialogs":{"total":200,"correct":134},"responses":{"total":2358,"correct":2290}}},{"index":8800,"runtimeInSeconds":10127.541,"objectiveValue":-208.02448333016903,"trainingStats":{"dialogs":{"total":200,"correct":173},"responses":{"total":2434,"correct":2407}},"devStats":{"dialogs":{"total":200,"correct":136},"responses":{"total":2358,"correct":2291}}},{"index":9000,"runtimeInSeconds":10352.675,"objectiveValue":-70.54599378102824,"trainingStats":{"dialogs":{"total":200,"correct":178},"responses":{"total":2434,"correct":2412}},"devStats":{"dialogs":{"total":200,"correct":147},"responses":{"total":2358,"correct":2303}}},{"index":9200,"runtimeInSeconds":10575.146,"objectiveValue":-241.25996247758246,"trainingStats":{"dialogs":{"total":200,"correct":141},"responses":{"total":2434,"correct":2369}},"devStats":{"dialogs":{"total":200,"correct":96},"responses":{"total":2358,"correct":2245}}},{"index":9400,"runtimeInSeconds":10794.965,"objectiveValue":-194.11832084258464,"trainingStats":{"dialogs":{"total":200,"correct":171},"responses":{"total":2434,"correct":2404}},"devStats":{"dialogs":{"total":200,"correct":157},"responses":{"total":2358,"correct":2314}}},{"index":9600,"runtimeInSeconds":11015.27,"objectiveValue":-87.97313956231876,"trainingStats":{"dialogs":{"total":200,"correct":170},"responses":{"total":2434,"correct":2403}},"devStats":{"dialogs":{"total":200,"correct":141},"responses":{"total":2358,"correct":2299}}},{"index":9800,"runtimeInSeconds":11234.442,"objectiveValue":-146.52409893722142,"trainingStats":{"dialogs":{"total":200,"correct":189},"responses":{"total":2434,"correct":2423}},"devStats":{"dialogs":{"total":200,"correct":172},"responses":{"total":2358,"correct":2330}}},{"index":10000,"runtimeInSeconds":11456.174,"objectiveValue":-129.08515711294763,"trainingStats":{"dialogs":{"total":200,"correct":176},"responses":{"total":2434,"correct":2407}},"devStats":{"dialogs":{"total":200,"correct":150},"responses":{"total":2358,"correct":2305}}},{"index":10200,"runtimeInSeconds":11677.728,"objectiveValue":-53.13026605230643,"trainingStats":{"dialogs":{"total":200,"correct":177},"responses":{"total":2434,"correct":2411}},"devStats":{"dialogs":{"total":200,"correct":145},"responses":{"total":2358,"correct":2302}}},{"index":10400,"runtimeInSeconds":11899.141,"objectiveValue":-54.44024596876646,"trainingStats":{"dialogs":{"total":200,"correct":178},"responses":{"total":2434,"correct":2412}},"devStats":{"dialogs":{"total":200,"correct":151},"responses":{"total":2358,"correct":2308}}},{"index":10600,"runtimeInSeconds":12122.47,"objectiveValue":-66.47949564608335,"trainingStats":{"dialogs":{"total":200,"correct":182},"responses":{"total":2434,"correct":2416}},"devStats":{"dialogs":{"total":200,"correct":166},"responses":{"total":2358,"correct":2324}}},{"index":10800,"runtimeInSeconds":12343.512,"objectiveValue":-109.99308916184552,"trainingStats":{"dialogs":{"total":200,"correct":186},"responses":{"total":2434,"correct":2420}},"devStats":{"dialogs":{"total":200,"correct":168},"responses":{"total":2358,"correct":2326}}},{"index":11000,"runtimeInSeconds":12562.536,"objectiveValue":-56.541377453793054,"trainingStats":{"dialogs":{"total":200,"correct":190},"responses":{"total":2434,"correct":2424}},"devStats":{"dialogs":{"total":200,"correct":170},"responses":{"total":2358,"correct":2327}}},{"index":11200,"runtimeInSeconds":12784.785,"objectiveValue":-41.03676695072874,"trainingStats":{"dialogs":{"total":200,"correct":189},"responses":{"total":2434,"correct":2423}},"devStats":{"dialogs":{"total":200,"correct":168},"responses":{"total":2358,"correct":2324}}},{"index":11400,"runtimeInSeconds":13011.852,"objectiveValue":-329.90901395560644,"trainingStats":{"dialogs":{"total":200,"correct":155},"responses":{"total":2434,"correct":2389}},"devStats":{"dialogs":{"total":200,"correct":135},"responses":{"total":2358,"correct":2290}}},{"index":11600,"runtimeInSeconds":13235.86,"objectiveValue":-199.75680768643934,"trainingStats":{"dialogs":{"total":200,"correct":169},"responses":{"total":2434,"correct":2402}},"devStats":{"dialogs":{"total":200,"correct":154},"responses":{"total":2358,"correct":2306}}},{"index":11800,"runtimeInSeconds":13459.798,"objectiveValue":-116.4523312533301,"trainingStats":{"dialogs":{"total":200,"correct":179},"responses":{"total":2434,"correct":2413}},"devStats":{"dialogs":{"total":200,"correct":154},"responses":{"total":2358,"correct":2311}}},{"index":12000,"runtimeInSeconds":13685.392,"objectiveValue":-72.25549213229333,"trainingStats":{"dialogs":{"total":200,"correct":178},"responses":{"total":2434,"correct":2412}},"devStats":{"dialogs":{"total":200,"correct":171},"responses":{"total":2358,"correct":2329}}},{"index":12200,"runtimeInSeconds":13906.204,"objectiveValue":-209.07969594116827,"trainingStats":{"dialogs":{"total":200,"correct":171},"responses":{"total":2434,"correct":2405}},"devStats":{"dialogs":{"total":200,"correct":158},"responses":{"total":2358,"correct":2315}}},{"index":12400,"runtimeInSeconds":14131.631,"objectiveValue":-68.61151671284827,"trainingStats":{"dialogs":{"total":200,"correct":168},"responses":{"total":2434,"correct":2402}},"devStats":{"dialogs":{"total":200,"correct":160},"responses":{"total":2358,"correct":2317}}},{"index":12600,"runtimeInSeconds":14353.493,"objectiveValue":-70.81209340325263,"trainingStats":{"dialogs":{"total":200,"correct":187},"responses":{"total":2434,"correct":2421}},"devStats":{"dialogs":{"total":200,"correct":168},"responses":{"total":2358,"correct":2326}}},{"index":12800,"runtimeInSeconds":14574.779,"objectiveValue":-42.47943599411818,"trainingStats":{"dialogs":{"total":200,"correct":189},"responses":{"total":2434,"correct":2423}},"devStats":{"dialogs":{"total":200,"correct":181},"responses":{"total":2358,"correct":2339}}},{"index":13000,"runtimeInSeconds":14797.506,"objectiveValue":-26.175377102354947,"trainingStats":{"dialogs":{"total":200,"correct":193},"responses":{"total":2434,"correct":2427}},"devStats":{"dialogs":{"total":200,"correct":181},"responses":{"total":2358,"correct":2338}}},{"index":13200,"runtimeInSeconds":15019.995,"objectiveValue":-41.52313918430453,"trainingStats":{"dialogs":{"total":200,"correct":195},"responses":{"total":2434,"correct":2428}},"devStats":{"dialogs":{"total":200,"correct":185},"responses":{"total":2358,"correct":2343}}},{"index":13400,"runtimeInSeconds":15240.661,"objectiveValue":-103.48647589896507,"trainingStats":{"dialogs":{"total":200,"correct":194},"responses":{"total":2434,"correct":2428}},"devStats":{"dialogs":{"total":200,"correct":186},"responses":{"total":2358,"correct":2344}}},{"index":13600,"runtimeInSeconds":15462.441,"objectiveValue":-65.59103419464299,"trainingStats":{"dialogs":{"total":200,"correct":190},"responses":{"total":2434,"correct":2424}},"devStats":{"dialogs":{"total":200,"correct":179},"responses":{"total":2358,"correct":2337}}},{"index":13800,"runtimeInSeconds":15685.209,"objectiveValue":-213.2526610559255,"trainingStats":{"dialogs":{"total":200,"correct":118},"responses":{"total":2434,"correct":2341}},"devStats":{"dialogs":{"total":200,"correct":111},"responses":{"total":2358,"correct":2261}}},{"index":14000,"runtimeInSeconds":15909.55,"objectiveValue":-44.20958838845671,"trainingStats":{"dialogs":{"total":200,"correct":189},"responses":{"total":2434,"correct":2423}},"devStats":{"dialogs":{"total":200,"correct":181},"responses":{"total":2358,"correct":2339}}},{"index":14200,"runtimeInSeconds":16132.486,"objectiveValue":-27.10614026595585,"trainingStats":{"dialogs":{"total":200,"correct":197},"responses":{"total":2434,"correct":2431}},"devStats":{"dialogs":{"total":200,"correct":174},"responses":{"total":2358,"correct":2332}}},{"index":14400,"runtimeInSeconds":16356.518,"objectiveValue":-58.644910362145175,"trainingStats":{"dialogs":{"total":200,"correct":193},"responses":{"total":2434,"correct":2427}},"devStats":{"dialogs":{"total":200,"correct":179},"responses":{"total":2358,"correct":2337}}},{"index":14600,"runtimeInSeconds":16580.267,"objectiveValue":-105.6747540188713,"trainingStats":{"dialogs":{"total":200,"correct":185},"responses":{"total":2434,"correct":2419}},"devStats":{"dialogs":{"total":200,"correct":175},"responses":{"total":2358,"correct":2333}}},{"index":14800,"runtimeInSeconds":16804.482,"objectiveValue":-13.859901304694722,"trainingStats":{"dialogs":{"total":200,"correct":199},"responses":{"total":2434,"correct":2433}},"devStats":{"dialogs":{"total":200,"correct":187},"responses":{"total":2358,"correct":2345}}},{"index":15000,"runtimeInSeconds":17026.887,"objectiveValue":-30.223733260370945,"trainingStats":{"dialogs":{"total":200,"correct":198},"responses":{"total":2434,"correct":2432}},"devStats":{"dialogs":{"total":200,"correct":194},"responses":{"total":2358,"correct":2352}}},{"index":15200,"runtimeInSeconds":17248.651,"objectiveValue":-13.295302712384894,"trainingStats":{"dialogs":{"total":200,"correct":194},"responses":{"total":2434,"correct":2428}},"devStats":{"dialogs":{"total":200,"correct":186},"responses":{"total":2358,"correct":2344}}},{"index":15400,"runtimeInSeconds":17473.085,"objectiveValue":-19.897394351439587,"trainingStats":{"dialogs":{"total":200,"correct":193},"responses":{"total":2434,"correct":2427}},"devStats":{"dialogs":{"total":200,"correct":187},"responses":{"total":2358,"correct":2345}}},{"index":15600,"runtimeInSeconds":17696.261,"objectiveValue":-15.306023012753275,"trainingStats":{"dialogs":{"total":200,"correct":196},"responses":{"total":2434,"correct":2430}},"devStats":{"dialogs":{"total":200,"correct":181},"responses":{"total":2358,"correct":2339}}},{"index":15800,"runtimeInSeconds":17922.997,"objectiveValue":-41.97743360832004,"trainingStats":{"dialogs":{"total":200,"correct":196},"responses":{"total":2434,"correct":2430}},"devStats":{"dialogs":{"total":200,"correct":190},"responses":{"total":2358,"correct":2348}}},{"index":16000,"runtimeInSeconds":18144.719,"objectiveValue":-12.743706732661995,"trainingStats":{"dialogs":{"total":200,"correct":199},"responses":{"total":2434,"correct":2433}},"devStats":{"dialogs":{"total":200,"correct":190},"responses":{"total":2358,"correct":2348}}},{"index":16200,"runtimeInSeconds":18366.614,"objectiveValue":-9.645173216820622,"trainingStats":{"dialogs":{"total":200,"correct":198},"responses":{"total":2434,"correct":2432}},"devStats":{"dialogs":{"total":200,"correct":193},"responses":{"total":2358,"correct":2351}}},{"index":16400,"runtimeInSeconds":18591.16,"objectiveValue":-12.928887610394504,"trainingStats":{"dialogs":{"total":200,"correct":196},"responses":{"total":2434,"correct":2430}},"devStats":{"dialogs":{"total":200,"correct":194},"responses":{"total":2358,"correct":2352}}},{"index":16600,"runtimeInSeconds":18816.029,"objectiveValue":-8.20928940272403,"trainingStats":{"dialogs":{"total":200,"correct":194},"responses":{"total":2434,"correct":2428}},"devStats":{"dialogs":{"total":200,"correct":196},"responses":{"total":2358,"correct":2354}}},{"index":16800,"runtimeInSeconds":19042.275,"objectiveValue":-5.531103237786285,"trainingStats":{"dialogs":{"total":200,"correct":199},"responses":{"total":2434,"correct":2433}},"devStats":{"dialogs":{"total":200,"correct":193},"responses":{"total":2358,"correct":2351}}},{"index":17000,"runtimeInSeconds":19262.767,"objectiveValue":-9.806160649256359,"trainingStats":{"dialogs":{"total":200,"correct":198},"responses":{"total":2434,"correct":2432}},"devStats":{"dialogs":{"total":200,"correct":191},"responses":{"total":2358,"correct":2349}}},{"index":17200,"runtimeInSeconds":19486.508,"objectiveValue":-1131.349905742343,"trainingStats":{"dialogs":{"total":200,"correct":133},"responses":{"total":2434,"correct":2362}},"devStats":{"dialogs":{"total":200,"correct":108},"responses":{"total":2358,"correct":2260}}},{"index":17400,"runtimeInSeconds":19709.261,"objectiveValue":-67.48347494755382,"trainingStats":{"dialogs":{"total":200,"correct":187},"responses":{"total":2434,"correct":2421}},"devStats":{"dialogs":{"total":200,"correct":177},"responses":{"total":2358,"correct":2335}}},{"index":17600,"runtimeInSeconds":19931.631,"objectiveValue":-39.99501602145673,"trainingStats":{"dialogs":{"total":200,"correct":196},"responses":{"total":2434,"correct":2430}},"devStats":{"dialogs":{"total":200,"correct":188},"responses":{"total":2358,"correct":2346}}},{"index":17800,"runtimeInSeconds":20154.348,"objectiveValue":-22.10843602533886,"trainingStats":{"dialogs":{"total":200,"correct":193},"responses":{"total":2434,"correct":2427}},"devStats":{"dialogs":{"total":200,"correct":186},"responses":{"total":2358,"correct":2344}}},{"index":18000,"runtimeInSeconds":20376.578,"objectiveValue":-31.533629226219233,"trainingStats":{"dialogs":{"total":200,"correct":195},"responses":{"total":2434,"correct":2429}},"devStats":{"dialogs":{"total":200,"correct":192},"responses":{"total":2358,"correct":2350}}},{"index":18200,"runtimeInSeconds":20597.831,"objectiveValue":-11.148051067289725,"trainingStats":{"dialogs":{"total":200,"correct":194},"responses":{"total":2434,"correct":2428}},"devStats":{"dialogs":{"total":200,"correct":188},"responses":{"total":2358,"correct":2345}}},{"index":18400,"runtimeInSeconds":20822.887,"objectiveValue":-10.590147285994886,"trainingStats":{"dialogs":{"total":200,"correct":196},"responses":{"total":2434,"correct":2430}},"devStats":{"dialogs":{"total":200,"correct":187},"responses":{"total":2358,"correct":2345}}},{"index":18600,"runtimeInSeconds":21043.77,"objectiveValue":-9.951059298787785,"trainingStats":{"dialogs":{"total":200,"correct":197},"responses":{"total":2434,"correct":2431}},"devStats":{"dialogs":{"total":200,"correct":187},"responses":{"total":2358,"correct":2343}}},{"index":18800,"runtimeInSeconds":21268.193,"objectiveValue":-16.496939144772348,"trainingStats":{"dialogs":{"total":200,"correct":198},"responses":{"total":2434,"correct":2432}},"devStats":{"dialogs":{"total":200,"correct":193},"responses":{"total":2358,"correct":2351}}},{"index":19000,"runtimeInSeconds":21494.55,"objectiveValue":-14.175388495925139,"trainingStats":{"dialogs":{"total":200,"correct":197},"responses":{"total":2434,"correct":2431}},"devStats":{"dialogs":{"total":200,"correct":190},"responses":{"total":2358,"correct":2348}}},{"index":19200,"runtimeInSeconds":21718.991,"objectiveValue":-24.29150027318228,"trainingStats":{"dialogs":{"total":200,"correct":199},"responses":{"total":2434,"correct":2433}},"devStats":{"dialogs":{"total":200,"correct":195},"responses":{"total":2358,"correct":2353}}},{"index":19400,"runtimeInSeconds":21942.807,"objectiveValue":-5.391470130296285,"trainingStats":{"dialogs":{"total":200,"correct":197},"responses":{"total":2434,"correct":2431}},"devStats":{"dialogs":{"total":200,"correct":189},"responses":{"total":2358,"correct":2347}}},{"index":19600,"runtimeInSeconds":22164.62,"objectiveValue":-4.95460553454169,"trainingStats":{"dialogs":{"total":200,"correct":199},"responses":{"total":2434,"correct":2433}},"devStats":{"dialogs":{"total":200,"correct":195},"responses":{"total":2358,"correct":2353}}},{"index":19800,"runtimeInSeconds":22388.133,"objectiveValue":-10.09091238091912,"trainingStats":{"dialogs":{"total":200,"correct":199},"responses":{"total":2434,"correct":2433}},"devStats":{"dialogs":{"total":200,"correct":198},"responses":{"total":2358,"correct":2356}}},{"index":20000,"runtimeInSeconds":22608.349,"objectiveValue":-4.648258761019209,"trainingStats":{"dialogs":{"total":200,"correct":199},"responses":{"total":2434,"correct":2433}},"devStats":{"dialogs":{"total":200,"correct":199},"responses":{"total":2358,"correct":2357}}},{"index":20200,"runtimeInSeconds":22830.562,"objectiveValue":-11.515901058895544,"trainingStats":{"dialogs":{"total":200,"correct":198},"responses":{"total":2434,"correct":2432}},"devStats":{"dialogs":{"total":200,"correct":198},"responses":{"total":2358,"correct":2356}}},{"index":20400,"runtimeInSeconds":23051.93,"objectiveValue":-5.152811613554318,"trainingStats":{"dialogs":{"total":200,"correct":199},"responses":{"total":2434,"correct":2433}},"devStats":{"dialogs":{"total":200,"correct":194},"responses":{"total":2358,"correct":2352}}},{"index":20600,"runtimeInSeconds":23275.163,"objectiveValue":-7.8876828904789935,"trainingStats":{"dialogs":{"total":200,"correct":198},"responses":{"total":2434,"correct":2432}},"devStats":{"dialogs":{"total":200,"correct":193},"responses":{"total":2358,"correct":2351}}},{"index":20800,"runtimeInSeconds":23495.807,"objectiveValue":-892.7501344963432,"trainingStats":{"dialogs":{"total":200,"correct":124},"responses":{"total":2434,"correct":2353}},"devStats":{"dialogs":{"total":200,"correct":111},"responses":{"total":2358,"correct":2256}}},{"index":21000,"runtimeInSeconds":23715.398,"objectiveValue":-42.90995015810902,"trainingStats":{"dialogs":{"total":200,"correct":180},"responses":{"total":2434,"correct":2414}},"devStats":{"dialogs":{"total":200,"correct":169},"responses":{"total":2358,"correct":2327}}},{"index":21200,"runtimeInSeconds":23940.596,"objectiveValue":-41.892080289161356,"trainingStats":{"dialogs":{"total":200,"correct":194},"responses":{"total":2434,"correct":2427}},"devStats":{"dialogs":{"total":200,"correct":185},"responses":{"total":2358,"correct":2343}}},{"index":21400,"runtimeInSeconds":24162.448,"objectiveValue":-43.12118627386587,"trainingStats":{"dialogs":{"total":200,"correct":200},"responses":{"total":2434,"correct":2434}},"devStats":{"dialogs":{"total":200,"correct":191},"responses":{"total":2358,"correct":2349}}},{"index":21600,"runtimeInSeconds":24389.044,"objectiveValue":-20.694684299512602,"trainingStats":{"dialogs":{"total":200,"correct":200},"responses":{"total":2434,"correct":2434}},"devStats":{"dialogs":{"total":200,"correct":190},"responses":{"total":2358,"correct":2348}}},{"index":21800,"runtimeInSeconds":24616.412,"objectiveValue":-19.473450444588728,"trainingStats":{"dialogs":{"total":200,"correct":196},"responses":{"total":2434,"correct":2430}},"devStats":{"dialogs":{"total":200,"correct":190},"responses":{"total":2358,"correct":2348}}},{"index":22000,"runtimeInSeconds":24844.22,"objectiveValue":-5.0295396093227565,"trainingStats":{"dialogs":{"total":200,"correct":195},"responses":{"total":2434,"correct":2429}},"devStats":{"dialogs":{"total":200,"correct":185},"responses":{"total":2358,"correct":2343}}},{"index":22200,"runtimeInSeconds":25069.808,"objectiveValue":-16.503150284669026,"trainingStats":{"dialogs":{"total":200,"correct":198},"responses":{"total":2434,"correct":2432}},"devStats":{"dialogs":{"total":200,"correct":194},"responses":{"total":2358,"correct":2352}}},{"index":22400,"runtimeInSeconds":25298.429,"objectiveValue":-6.165858138474843,"trainingStats":{"dialogs":{"total":200,"correct":199},"responses":{"total":2434,"correct":2433}},"devStats":{"dialogs":{"total":200,"correct":198},"responses":{"total":2358,"correct":2356}}},{"index":22600,"runtimeInSeconds":25524.276,"objectiveValue":-6.557495339538219,"trainingStats":{"dialogs":{"total":200,"correct":198},"responses":{"total":2434,"correct":2432}},"devStats":{"dialogs":{"total":200,"correct":191},"responses":{"total":2358,"correct":2349}}},{"index":22800,"runtimeInSeconds":25754.287,"objectiveValue":-14.484163030593713,"trainingStats":{"dialogs":{"total":200,"correct":199},"responses":{"total":2434,"correct":2433}},"devStats":{"dialogs":{"total":200,"correct":191},"responses":{"total":2358,"correct":2349}}},{"index":23000,"runtimeInSeconds":25978.798,"objectiveValue":-14.163422223917193,"trainingStats":{"dialogs":{"total":200,"correct":197},"responses":{"total":2434,"correct":2431}},"devStats":{"dialogs":{"total":200,"correct":197},"responses":{"total":2358,"correct":2355}}},{"index":23200,"runtimeInSeconds":26203.735,"objectiveValue":-8.014194305952035,"trainingStats":{"dialogs":{"total":200,"correct":198},"responses":{"total":2434,"correct":2432}},"devStats":{"dialogs":{"total":200,"correct":192},"responses":{"total":2358,"correct":2350}}},{"index":23400,"runtimeInSeconds":26430.629,"objectiveValue":-4.377133266299099,"trainingStats":{"dialogs":{"total":200,"correct":199},"responses":{"total":2434,"correct":2433}},"devStats":{"dialogs":{"total":200,"correct":193},"responses":{"total":2358,"correct":2351}}},{"index":23600,"runtimeInSeconds":26653.624,"objectiveValue":-3.128513350466334,"trainingStats":{"dialogs":{"total":200,"correct":199},"responses":{"total":2434,"correct":2433}},"devStats":{"dialogs":{"total":200,"correct":198},"responses":{"total":2358,"correct":2356}}},{"index":23800,"runtimeInSeconds":26874.256,"objectiveValue":-1.8998661079541628,"trainingStats":{"dialogs":{"total":200,"correct":200},"responses":{"total":2434,"correct":2434}},"devStats":{"dialogs":{"total":200,"correct":190},"responses":{"total":2358,"correct":2348}}},{"index":24000,"runtimeInSeconds":27103.372,"objectiveValue":-3.0298123665253716,"trainingStats":{"dialogs":{"total":200,"correct":197},"responses":{"total":2434,"correct":2431}},"devStats":{"dialogs":{"total":200,"correct":195},"responses":{"total":2358,"correct":2353}}},{"index":24200,"runtimeInSeconds":27325.95,"objectiveValue":-3.6919416882992917,"trainingStats":{"dialogs":{"total":200,"correct":199},"responses":{"total":2434,"correct":2433}},"devStats":{"dialogs":{"total":200,"correct":197},"responses":{"total":2358,"correct":2355}}},{"index":24400,"runtimeInSeconds":27550.314,"objectiveValue":-5.252669981334287,"trainingStats":{"dialogs":{"total":200,"correct":198},"responses":{"total":2434,"correct":2432}},"devStats":{"dialogs":{"total":200,"correct":193},"responses":{"total":2358,"correct":2351}}},{"index":24600,"runtimeInSeconds":27778.469,"objectiveValue":-2.8423484406305666,"trainingStats":{"dialogs":{"total":200,"correct":199},"responses":{"total":2434,"correct":2433}},"devStats":{"dialogs":{"total":200,"correct":196},"responses":{"total":2358,"correct":2354}}},{"index":24800,"runtimeInSeconds":28004.227,"objectiveValue":-2.624127998785555,"trainingStats":{"dialogs":{"total":200,"correct":199},"responses":{"total":2434,"correct":2433}},"devStats":{"dialogs":{"total":200,"correct":196},"responses":{"total":2358,"correct":2354}}},{"index":25000,"runtimeInSeconds":28228.429,"objectiveValue":-1.5980321340530508,"trainingStats":{"dialogs":{"total":200,"correct":200},"responses":{"total":2434,"correct":2434}},"devStats":{"dialogs":{"total":200,"correct":193},"responses":{"total":2358,"correct":2350}}},{"index":25200,"runtimeInSeconds":28455.492,"objectiveValue":-34.92070181928824,"trainingStats":{"dialogs":{"total":200,"correct":194},"responses":{"total":2434,"correct":2427}},"devStats":{"dialogs":{"total":200,"correct":183},"responses":{"total":2358,"correct":2341}}},{"index":25400,"runtimeInSeconds":28677.678,"objectiveValue":-10.714906794511556,"trainingStats":{"dialogs":{"total":200,"correct":200},"responses":{"total":2434,"correct":2434}},"devStats":{"dialogs":{"total":200,"correct":195},"responses":{"total":2358,"correct":2353}}},{"index":25600,"runtimeInSeconds":28906.779,"objectiveValue":-10.826666940268542,"trainingStats":{"dialogs":{"total":200,"correct":199},"responses":{"total":2434,"correct":2433}},"devStats":{"dialogs":{"total":200,"correct":192},"responses":{"total":2358,"correct":2350}}},{"index":25800,"runtimeInSeconds":29129.709,"objectiveValue":-7.82562998467808,"trainingStats":{"dialogs":{"total":200,"correct":197},"responses":{"total":2434,"correct":2431}},"devStats":{"dialogs":{"total":200,"correct":196},"responses":{"total":2358,"correct":2354}}},{"index":26000,"runtimeInSeconds":29358.102,"objectiveValue":-12.082065135218883,"trainingStats":{"dialogs":{"total":200,"correct":199},"responses":{"total":2434,"correct":2433}},"devStats":{"dialogs":{"total":200,"correct":196},"responses":{"total":2358,"correct":2354}}},{"index":26200,"runtimeInSeconds":29587.527,"objectiveValue":-3.952285965251223,"trainingStats":{"dialogs":{"total":200,"correct":200},"responses":{"total":2434,"correct":2434}},"devStats":{"dialogs":{"total":200,"correct":197},"responses":{"total":2358,"correct":2355}}},{"index":26400,"runtimeInSeconds":29814.855,"objectiveValue":-7.220340193958416,"trainingStats":{"dialogs":{"total":200,"correct":200},"responses":{"total":2434,"correct":2434}},"devStats":{"dialogs":{"total":200,"correct":193},"responses":{"total":2358,"correct":2351}}},{"index":26600,"runtimeInSeconds":30040.206,"objectiveValue":-5.092542541117338,"trainingStats":{"dialogs":{"total":200,"correct":199},"responses":{"total":2434,"correct":2433}},"devStats":{"dialogs":{"total":200,"correct":197},"responses":{"total":2358,"correct":2355}}},{"index":26800,"runtimeInSeconds":30269.204,"objectiveValue":-2.7201029872671354,"trainingStats":{"dialogs":{"total":200,"correct":197},"responses":{"total":2434,"correct":2431}},"devStats":{"dialogs":{"total":200,"correct":200},"responses":{"total":2358,"correct":2358}}},{"index":27000,"runtimeInSeconds":30495.088,"objectiveValue":-4.311752092441982,"trainingStats":{"dialogs":{"total":200,"correct":199},"responses":{"total":2434,"correct":2433}},"devStats":{"dialogs":{"total":200,"correct":197},"responses":{"total":2358,"correct":2355}}},{"index":27200,"runtimeInSeconds":30719.387,"objectiveValue":-3.566443006255832,"trainingStats":{"dialogs":{"total":200,"correct":198},"responses":{"total":2434,"correct":2432}},"devStats":{"dialogs":{"total":200,"correct":197},"responses":{"total":2358,"correct":2355}}},{"index":27400,"runtimeInSeconds":30942.915,"objectiveValue":-2.4238669932334242,"trainingStats":{"dialogs":{"total":200,"correct":199},"responses":{"total":2434,"correct":2433}},"devStats":{"dialogs":{"total":200,"correct":196},"responses":{"total":2358,"correct":2354}}},{"index":27600,"runtimeInSeconds":31165.904,"objectiveValue":-2.391950470367119,"trainingStats":{"dialogs":{"total":200,"correct":200},"responses":{"total":2434,"correct":2434}},"devStats":{"dialogs":{"total":200,"correct":198},"responses":{"total":2358,"correct":2356}}},{"index":27800,"runtimeInSeconds":31393.673,"objectiveValue":-3.6554985731202,"trainingStats":{"dialogs":{"total":200,"correct":198},"responses":{"total":2434,"correct":2432}},"devStats":{"dialogs":{"total":200,"correct":196},"responses":{"total":2358,"correct":2354}}},{"index":28000,"runtimeInSeconds":31619.221,"objectiveValue":-1.5717792500996908,"trainingStats":{"dialogs":{"total":200,"correct":200},"responses":{"total":2434,"correct":2434}},"devStats":{"dialogs":{"total":200,"correct":198},"responses":{"total":2358,"correct":2356}}},{"index":28200,"runtimeInSeconds":31846.066,"objectiveValue":-2.84186273752783,"trainingStats":{"dialogs":{"total":200,"correct":200},"responses":{"total":2434,"correct":2434}},"devStats":{"dialogs":{"total":200,"correct":197},"responses":{"total":2358,"correct":2355}}},{"index":28400,"runtimeInSeconds":32074.512,"objectiveValue":-3.246572499995396,"trainingStats":{"dialogs":{"total":200,"correct":200},"responses":{"total":2434,"correct":2434}},"devStats":{"dialogs":{"total":200,"correct":199},"responses":{"total":2358,"correct":2357}}},{"index":28600,"runtimeInSeconds":32300.196,"objectiveValue":-1.359426065930333,"trainingStats":{"dialogs":{"total":200,"correct":200},"responses":{"total":2434,"correct":2434}},"devStats":{"dialogs":{"total":200,"correct":199},"responses":{"total":2358,"correct":2357}}},{"index":28800,"runtimeInSeconds":32524.63,"objectiveValue":-1.4325117052598912,"trainingStats":{"dialogs":{"total":200,"correct":200},"responses":{"total":2434,"correct":2434}},"devStats":{"dialogs":{"total":200,"correct":198},"responses":{"total":2358,"correct":2356}}},{"index":29000,"runtimeInSeconds":32749.678,"objectiveValue":-1.505455031833001,"trainingStats":{"dialogs":{"total":200,"correct":200},"responses":{"total":2434,"correct":2434}},"devStats":{"dialogs":{"total":200,"correct":198},"responses":{"total":2358,"correct":2356}}},{"index":29200,"runtimeInSeconds":32975.493,"objectiveValue":-1.0717593562112178,"trainingStats":{"dialogs":{"total":200,"correct":200},"responses":{"total":2434,"correct":2434}},"devStats":{"dialogs":{"total":200,"correct":197},"responses":{"total":2358,"correct":2355}}},{"index":29400,"runtimeInSeconds":33200.735,"objectiveValue":-0.9381841881952461,"trainingStats":{"dialogs":{"total":200,"correct":200},"responses":{"total":2434,"correct":2434}},"devStats":{"dialogs":{"total":200,"correct":197},"responses":{"total":2358,"correct":2355}}},{"index":29600,"runtimeInSeconds":33426.71,"objectiveValue":-37.63087424479288,"trainingStats":{"dialogs":{"total":200,"correct":188},"responses":{"total":2434,"correct":2422}},"devStats":{"dialogs":{"total":200,"correct":183},"responses":{"total":2358,"correct":2339}}},{"index":29800,"runtimeInSeconds":33652.741,"objectiveValue":-58.14737119629028,"trainingStats":{"dialogs":{"total":200,"correct":195},"responses":{"total":2434,"correct":2429}},"devStats":{"dialogs":{"total":200,"correct":188},"responses":{"total":2358,"correct":2346}}},{"index":30000,"runtimeInSeconds":33882.884,"objectiveValue":-13.533015076462174,"trainingStats":{"dialogs":{"total":200,"correct":199},"responses":{"total":2434,"correct":2433}},"devStats":{"dialogs":{"total":200,"correct":191},"responses":{"total":2358,"correct":2349}}},{"index":30200,"runtimeInSeconds":34111.726,"objectiveValue":-18.47435077772211,"trainingStats":{"dialogs":{"total":200,"correct":195},"responses":{"total":2434,"correct":2429}},"devStats":{"dialogs":{"total":200,"correct":193},"responses":{"total":2358,"correct":2351}}},{"index":30400,"runtimeInSeconds":34341.481,"objectiveValue":-8.919729659369075,"trainingStats":{"dialogs":{"total":200,"correct":195},"responses":{"total":2434,"correct":2429}},"devStats":{"dialogs":{"total":200,"correct":195},"responses":{"total":2358,"correct":2353}}},{"index":30600,"runtimeInSeconds":34569.403,"objectiveValue":-14.651732893784233,"trainingStats":{"dialogs":{"total":200,"correct":199},"responses":{"total":2434,"correct":2433}},"devStats":{"dialogs":{"total":200,"correct":195},"responses":{"total":2358,"correct":2353}}},{"index":30800,"runtimeInSeconds":34796.108,"objectiveValue":-7.520252474036447,"trainingStats":{"dialogs":{"total":200,"correct":199},"responses":{"total":2434,"correct":2433}},"devStats":{"dialogs":{"total":200,"correct":196},"responses":{"total":2358,"correct":2354}}},{"index":31000,"runtimeInSeconds":35019.421,"objectiveValue":-5.068562642598441,"trainingStats":{"dialogs":{"total":200,"correct":197},"responses":{"total":2434,"correct":2431}},"devStats":{"dialogs":{"total":200,"correct":194},"responses":{"total":2358,"correct":2352}}},{"index":31200,"runtimeInSeconds":35248.399,"objectiveValue":-4.941646528542128,"trainingStats":{"dialogs":{"total":200,"correct":200},"responses":{"total":2434,"correct":2434}},"devStats":{"dialogs":{"total":200,"correct":199},"responses":{"total":2358,"correct":2357}}},{"index":31400,"runtimeInSeconds":35477.532,"objectiveValue":-3.615960506942357,"trainingStats":{"dialogs":{"total":200,"correct":200},"responses":{"total":2434,"correct":2434}},"devStats":{"dialogs":{"total":200,"correct":199},"responses":{"total":2358,"correct":2357}}},{"index":31600,"runtimeInSeconds":35710.762,"objectiveValue":-3.4436517025615268,"trainingStats":{"dialogs":{"total":200,"correct":199},"responses":{"total":2434,"correct":2433}},"devStats":{"dialogs":{"total":200,"correct":196},"responses":{"total":2358,"correct":2354}}},{"index":31800,"runtimeInSeconds":35937.746,"objectiveValue":-4.909653520120011,"trainingStats":{"dialogs":{"total":200,"correct":199},"responses":{"total":2434,"correct":2433}},"devStats":{"dialogs":{"total":200,"correct":198},"responses":{"total":2358,"correct":2356}}},{"index":32000,"runtimeInSeconds":36170.136,"objectiveValue":-5.323546616077798,"trainingStats":{"dialogs":{"total":200,"correct":199},"responses":{"total":2434,"correct":2433}},"devStats":{"dialogs":{"total":200,"correct":199},"responses":{"total":2358,"correct":2357}}},{"index":32200,"runtimeInSeconds":36402.299,"objectiveValue":-3.0264740794424343,"trainingStats":{"dialogs":{"total":200,"correct":199},"responses":{"total":2434,"correct":2433}},"devStats":{"dialogs":{"total":200,"correct":197},"responses":{"total":2358,"correct":2355}}},{"index":32400,"runtimeInSeconds":36632.747,"objectiveValue":-4.390581441963201,"trainingStats":{"dialogs":{"total":200,"correct":200},"responses":{"total":2434,"correct":2434}},"devStats":{"dialogs":{"total":200,"correct":197},"responses":{"total":2358,"correct":2355}}},{"index":32600,"runtimeInSeconds":36859.878,"objectiveValue":-2.046280200166369,"trainingStats":{"dialogs":{"total":200,"correct":200},"responses":{"total":2434,"correct":2434}},"devStats":{"dialogs":{"total":200,"correct":198},"responses":{"total":2358,"correct":2356}}},{"index":32800,"runtimeInSeconds":37088.112,"objectiveValue":-2.9758195456779983,"trainingStats":{"dialogs":{"total":200,"correct":200},"responses":{"total":2434,"correct":2434}},"devStats":{"dialogs":{"total":200,"correct":198},"responses":{"total":2358,"correct":2356}}},{"index":33000,"runtimeInSeconds":37314.599,"objectiveValue":-2.598649200738275,"trainingStats":{"dialogs":{"total":200,"correct":199},"responses":{"total":2434,"correct":2433}},"devStats":{"dialogs":{"total":200,"correct":200},"responses":{"total":2358,"correct":2358}}},{"index":33200,"runtimeInSeconds":37542.078,"objectiveValue":-2.8188690113165187,"trainingStats":{"dialogs":{"total":200,"correct":200},"responses":{"total":2434,"correct":2434}},"devStats":{"dialogs":{"total":200,"correct":197},"responses":{"total":2358,"correct":2355}}},{"index":33400,"runtimeInSeconds":37771.06,"objectiveValue":-2.8351619102964203,"trainingStats":{"dialogs":{"total":200,"correct":200},"responses":{"total":2434,"correct":2434}},"devStats":{"dialogs":{"total":200,"correct":199},"responses":{"total":2358,"correct":2357}}},{"index":33600,"runtimeInSeconds":37996.074,"objectiveValue":-1.4146315079860379,"trainingStats":{"dialogs":{"total":200,"correct":200},"responses":{"total":2434,"correct":2434}},"devStats":{"dialogs":{"total":200,"correct":198},"responses":{"total":2358,"correct":2356}}},{"index":33800,"runtimeInSeconds":38227.504,"objectiveValue":-2.78865747295692,"trainingStats":{"dialogs":{"total":200,"correct":199},"responses":{"total":2434,"correct":2433}},"devStats":{"dialogs":{"total":200,"correct":200},"responses":{"total":2358,"correct":2358}}},{"index":34000,"runtimeInSeconds":38456.578,"objectiveValue":-3.980348598302166,"trainingStats":{"dialogs":{"total":200,"correct":200},"responses":{"total":2434,"correct":2434}},"devStats":{"dialogs":{"total":200,"correct":199},"responses":{"total":2358,"correct":2357}}},{"index":34200,"runtimeInSeconds":38688.888,"objectiveValue":-1.0540146429641266,"trainingStats":{"dialogs":{"total":200,"correct":199},"responses":{"total":2434,"correct":2433}},"devStats":{"dialogs":{"total":200,"correct":199},"responses":{"total":2358,"correct":2357}}},{"index":34400,"runtimeInSeconds":38917.852,"objectiveValue":-0.7200176803880796,"trainingStats":{"dialogs":{"total":200,"correct":200},"responses":{"total":2434,"correct":2434}},"devStats":{"dialogs":{"total":200,"correct":198},"responses":{"total":2358,"correct":2356}}},{"index":34600,"runtimeInSeconds":39143.667,"objectiveValue":-0.6349575977405483,"trainingStats":{"dialogs":{"total":200,"correct":199},"responses":{"total":2434,"correct":2433}},"devStats":{"dialogs":{"total":200,"correct":199},"responses":{"total":2358,"correct":2357}}},{"index":34800,"runtimeInSeconds":39374.321,"objectiveValue":-1.3521740508620668,"trainingStats":{"dialogs":{"total":200,"correct":199},"responses":{"total":2434,"correct":2433}},"devStats":{"dialogs":{"total":200,"correct":200},"responses":{"total":2358,"correct":2358}}},{"index":35000,"runtimeInSeconds":39601.297,"objectiveValue":-0.7379304514141242,"trainingStats":{"dialogs":{"total":200,"correct":200},"responses":{"total":2434,"correct":2434}},"devStats":{"dialogs":{"total":200,"correct":197},"responses":{"total":2358,"correct":2355}}},{"index":35200,"runtimeInSeconds":39826.281,"objectiveValue":-0.9639775428545901,"trainingStats":{"dialogs":{"total":200,"correct":200},"responses":{"total":2434,"correct":2434}},"devStats":{"dialogs":{"total":200,"correct":198},"responses":{"total":2358,"correct":2356}}},{"index":35400,"runtimeInSeconds":40054.597,"objectiveValue":-0.842098067927193,"trainingStats":{"dialogs":{"total":200,"correct":200},"responses":{"total":2434,"correct":2434}},"devStats":{"dialogs":{"total":200,"correct":199},"responses":{"total":2358,"correct":2357}}},{"index":35600,"runtimeInSeconds":40282.295,"objectiveValue":-1.2411593731553623,"trainingStats":{"dialogs":{"total":200,"correct":200},"responses":{"total":2434,"correct":2434}},"devStats":{"dialogs":{"total":200,"correct":200},"responses":{"total":2358,"correct":2358}}},{"index":35800,"runtimeInSeconds":40511.095,"objectiveValue":-0.5230497235598274,"trainingStats":{"dialogs":{"total":200,"correct":200},"responses":{"total":2434,"correct":2434}},"devStats":{"dialogs":{"total":200,"correct":199},"responses":{"total":2358,"correct":2357}}},{"index":36000,"runtimeInSeconds":40742.19,"objectiveValue":-1.3249990864162222,"trainingStats":{"dialogs":{"total":200,"correct":200},"responses":{"total":2434,"correct":2434}},"devStats":{"dialogs":{"total":200,"correct":199},"responses":{"total":2358,"correct":2357}}},{"index":36200,"runtimeInSeconds":40969.073,"objectiveValue":-0.671829681094313,"trainingStats":{"dialogs":{"total":200,"correct":200},"responses":{"total":2434,"correct":2434}},"devStats":{"dialogs":{"total":200,"correct":199},"responses":{"total":2358,"correct":2357}}},{"index":36400,"runtimeInSeconds":41194.363,"objectiveValue":-0.8013725199816788,"trainingStats":{"dialogs":{"total":200,"correct":200},"responses":{"total":2434,"correct":2434}},"devStats":{"dialogs":{"total":200,"correct":198},"responses":{"total":2358,"correct":2356}}},{"index":36600,"runtimeInSeconds":41421.648,"objectiveValue":-0.2859398825115152,"trainingStats":{"dialogs":{"total":200,"correct":200},"responses":{"total":2434,"correct":2434}},"devStats":{"dialogs":{"total":200,"correct":199},"responses":{"total":2358,"correct":2357}}},{"index":36800,"runtimeInSeconds":41649.834,"objectiveValue":-0.27985126142788636,"trainingStats":{"dialogs":{"total":200,"correct":200},"responses":{"total":2434,"correct":2434}},"devStats":{"dialogs":{"total":200,"correct":199},"responses":{"total":2358,"correct":2357}}},{"index":37000,"runtimeInSeconds":41877.569,"objectiveValue":-72.7904613818703,"trainingStats":{"dialogs":{"total":200,"correct":188},"responses":{"total":2434,"correct":2421}},"devStats":{"dialogs":{"total":200,"correct":174},"responses":{"total":2358,"correct":2332}}},{"index":37200,"runtimeInSeconds":42107.237,"objectiveValue":-32.10585979052761,"trainingStats":{"dialogs":{"total":200,"correct":197},"responses":{"total":2434,"correct":2431}},"devStats":{"dialogs":{"total":200,"correct":194},"responses":{"total":2358,"correct":2352}}},{"index":37400,"runtimeInSeconds":42333.103,"objectiveValue":-14.892221036656956,"trainingStats":{"dialogs":{"total":200,"correct":200},"responses":{"total":2434,"correct":2434}},"devStats":{"dialogs":{"total":200,"correct":195},"responses":{"total":2358,"correct":2353}}},{"index":37600,"runtimeInSeconds":42557.977,"objectiveValue":-4.015995947283631,"trainingStats":{"dialogs":{"total":200,"correct":197},"responses":{"total":2434,"correct":2431}},"devStats":{"dialogs":{"total":200,"correct":194},"responses":{"total":2358,"correct":2352}}},{"index":37800,"runtimeInSeconds":42779.587,"objectiveValue":-2.811562208276068,"trainingStats":{"dialogs":{"total":200,"correct":200},"responses":{"total":2434,"correct":2434}},"devStats":{"dialogs":{"total":200,"correct":197},"responses":{"total":2358,"correct":2355}}},{"index":38000,"runtimeInSeconds":43002.076,"objectiveValue":-4.867890448832422,"trainingStats":{"dialogs":{"total":200,"correct":199},"responses":{"total":2434,"correct":2433}},"devStats":{"dialogs":{"total":200,"correct":196},"responses":{"total":2358,"correct":2354}}},{"index":38200,"runtimeInSeconds":43230.916,"objectiveValue":-3.074727685254758,"trainingStats":{"dialogs":{"total":200,"correct":198},"responses":{"total":2434,"correct":2432}},"devStats":{"dialogs":{"total":200,"correct":199},"responses":{"total":2358,"correct":2357}}},{"index":38400,"runtimeInSeconds":43459.209,"objectiveValue":-3.1361563370977237,"trainingStats":{"dialogs":{"total":200,"correct":199},"responses":{"total":2434,"correct":2433}},"devStats":{"dialogs":{"total":200,"correct":196},"responses":{"total":2358,"correct":2354}}},{"index":38600,"runtimeInSeconds":43689.748,"objectiveValue":-3.7284377094646604,"trainingStats":{"dialogs":{"total":200,"correct":200},"responses":{"total":2434,"correct":2434}},"devStats":{"dialogs":{"total":200,"correct":196},"responses":{"total":2358,"correct":2354}}},{"index":38800,"runtimeInSeconds":43918.19,"objectiveValue":-5.242537726878806,"trainingStats":{"dialogs":{"total":200,"correct":200},"responses":{"total":2434,"correct":2434}},"devStats":{"dialogs":{"total":200,"correct":199},"responses":{"total":2358,"correct":2357}}},{"index":39000,"runtimeInSeconds":44147.762,"objectiveValue":-3.825505082598572,"trainingStats":{"dialogs":{"total":200,"correct":199},"responses":{"total":2434,"correct":2433}},"devStats":{"dialogs":{"total":200,"correct":199},"responses":{"total":2358,"correct":2357}}},{"index":39200,"runtimeInSeconds":44378.364,"objectiveValue":-2.0463967574809367,"trainingStats":{"dialogs":{"total":200,"correct":200},"responses":{"total":2434,"correct":2434}},"devStats":{"dialogs":{"total":200,"correct":196},"responses":{"total":2358,"correct":2354}}},{"index":39400,"runtimeInSeconds":44602.754,"objectiveValue":-1.1101602007792604,"trainingStats":{"dialogs":{"total":200,"correct":200},"responses":{"total":2434,"correct":2434}},"devStats":{"dialogs":{"total":200,"correct":197},"responses":{"total":2358,"correct":2355}}},{"index":39600,"runtimeInSeconds":44830.792,"objectiveValue":-1.0810449976962562,"trainingStats":{"dialogs":{"total":200,"correct":199},"responses":{"total":2434,"correct":2433}},"devStats":{"dialogs":{"total":200,"correct":199},"responses":{"total":2358,"correct":2357}}},{"index":39800,"runtimeInSeconds":45058.145,"objectiveValue":-0.8412888041762249,"trainingStats":{"dialogs":{"total":200,"correct":200},"responses":{"total":2434,"correct":2434}},"devStats":{"dialogs":{"total":200,"correct":199},"responses":{"total":2358,"correct":2357}}},{"index":40000,"runtimeInSeconds":45286.55,"objectiveValue":-1.2696890895018953,"trainingStats":{"dialogs":{"total":200,"correct":199},"responses":{"total":2434,"correct":2433}},"devStats":{"dialogs":{"total":200,"correct":199},"responses":{"total":2358,"correct":2357}}},{"index":40200,"runtimeInSeconds":45516.795,"objectiveValue":-0.6878074210139614,"trainingStats":{"dialogs":{"total":200,"correct":199},"responses":{"total":2434,"correct":2433}},"devStats":{"dialogs":{"total":200,"correct":198},"responses":{"total":2358,"correct":2356}}},{"index":40400,"runtimeInSeconds":45744.546,"objectiveValue":-1.04258036261681,"trainingStats":{"dialogs":{"total":200,"correct":200},"responses":{"total":2434,"correct":2434}},"devStats":{"dialogs":{"total":200,"correct":198},"responses":{"total":2358,"correct":2356}}},{"index":40600,"runtimeInSeconds":45978.296,"objectiveValue":-1.2677435989567085,"trainingStats":{"dialogs":{"total":200,"correct":200},"responses":{"total":2434,"correct":2434}},"devStats":{"dialogs":{"total":200,"correct":200},"responses":{"total":2358,"correct":2358}}},{"index":40800,"runtimeInSeconds":46207.107,"objectiveValue":-0.6934038685497135,"trainingStats":{"dialogs":{"total":200,"correct":199},"responses":{"total":2434,"correct":2433}},"devStats":{"dialogs":{"total":200,"correct":199},"responses":{"total":2358,"correct":2357}}},{"index":41000,"runtimeInSeconds":46436.003,"objectiveValue":-1.0708673807786169,"trainingStats":{"dialogs":{"total":200,"correct":200},"responses":{"total":2434,"correct":2434}},"devStats":{"dialogs":{"total":200,"correct":197},"responses":{"total":2358,"correct":2355}}},{"index":41200,"runtimeInSeconds":46662.721,"objectiveValue":-0.6927213636620372,"trainingStats":{"dialogs":{"total":200,"correct":200},"responses":{"total":2434,"correct":2434}},"devStats":{"dialogs":{"total":200,"correct":199},"responses":{"total":2358,"correct":2357}}},{"index":41400,"runtimeInSeconds":46892.751,"objectiveValue":-0.5160120143970011,"trainingStats":{"dialogs":{"total":200,"correct":200},"responses":{"total":2434,"correct":2434}},"devStats":{"dialogs":{"total":200,"correct":200},"responses":{"total":2358,"correct":2358}}},{"index":41600,"runtimeInSeconds":47119.544,"objectiveValue":-0.6493402913116342,"trainingStats":{"dialogs":{"total":200,"correct":200},"responses":{"total":2434,"correct":2434}},"devStats":{"dialogs":{"total":200,"correct":197},"responses":{"total":2358,"correct":2355}}},{"index":41800,"runtimeInSeconds":47346.687,"objectiveValue":-0.8060060228370586,"trainingStats":{"dialogs":{"total":200,"correct":200},"responses":{"total":2434,"correct":2434}},"devStats":{"dialogs":{"total":200,"correct":200},"responses":{"total":2358,"correct":2358}}},{"index":42000,"runtimeInSeconds":47579.202,"objectiveValue":-0.5859722729521588,"trainingStats":{"dialogs":{"total":200,"correct":200},"responses":{"total":2434,"correct":2434}},"devStats":{"dialogs":{"total":200,"correct":197},"responses":{"total":2358,"correct":2355}}},{"index":42200,"runtimeInSeconds":47807.598,"objectiveValue":-0.3038514265817156,"trainingStats":{"dialogs":{"total":200,"correct":200},"responses":{"total":2434,"correct":2434}},"devStats":{"dialogs":{"total":200,"correct":198},"responses":{"total":2358,"correct":2356}}},{"index":42400,"runtimeInSeconds":48036.532,"objectiveValue":-0.33320621238741316,"trainingStats":{"dialogs":{"total":200,"correct":200},"responses":{"total":2434,"correct":2434}},"devStats":{"dialogs":{"total":200,"correct":199},"responses":{"total":2358,"correct":2357}}},{"index":42600,"runtimeInSeconds":48263.428,"objectiveValue":-0.3194480489801959,"trainingStats":{"dialogs":{"total":200,"correct":200},"responses":{"total":2434,"correct":2434}},"devStats":{"dialogs":{"total":200,"correct":200},"responses":{"total":2358,"correct":2358}}},{"index":42800,"runtimeInSeconds":48494.127,"objectiveValue":-0.33899711838557534,"trainingStats":{"dialogs":{"total":200,"correct":200},"responses":{"total":2434,"correct":2434}},"devStats":{"dialogs":{"total":200,"correct":198},"responses":{"total":2358,"correct":2356}}},{"index":43000,"runtimeInSeconds":48725.754,"objectiveValue":-0.1891601725995961,"trainingStats":{"dialogs":{"total":200,"correct":200},"responses":{"total":2434,"correct":2434}},"devStats":{"dialogs":{"total":200,"correct":199},"responses":{"total":2358,"correct":2357}}},{"index":43200,"runtimeInSeconds":48961.402,"objectiveValue":-0.48484785866158875,"trainingStats":{"dialogs":{"total":200,"correct":200},"responses":{"total":2434,"correct":2434}},"devStats":{"dialogs":{"total":200,"correct":199},"responses":{"total":2358,"correct":2357}}},{"index":43400,"runtimeInSeconds":49190.201,"objectiveValue":-0.4319761355441603,"trainingStats":{"dialogs":{"total":200,"correct":200},"responses":{"total":2434,"correct":2434}},"devStats":{"dialogs":{"total":200,"correct":200},"responses":{"total":2358,"correct":2358}}},{"index":43600,"runtimeInSeconds":49417.886,"objectiveValue":-0.37748870986770294,"trainingStats":{"dialogs":{"total":200,"correct":200},"responses":{"total":2434,"correct":2434}},"devStats":{"dialogs":{"total":200,"correct":200},"responses":{"total":2358,"correct":2358}}},{"index":43800,"runtimeInSeconds":49652.742,"objectiveValue":-0.18015242303904186,"trainingStats":{"dialogs":{"total":200,"correct":200},"responses":{"total":2434,"correct":2434}},"devStats":{"dialogs":{"total":200,"correct":199},"responses":{"total":2358,"correct":2357}}},{"index":44000,"runtimeInSeconds":49881.096,"objectiveValue":-0.3406681188850837,"trainingStats":{"dialogs":{"total":200,"correct":200},"responses":{"total":2434,"correct":2434}},"devStats":{"dialogs":{"total":200,"correct":200},"responses":{"total":2358,"correct":2358}}},{"index":44200,"runtimeInSeconds":50109.273,"objectiveValue":-0.4859401488060824,"trainingStats":{"dialogs":{"total":200,"correct":200},"responses":{"total":2434,"correct":2434}},"devStats":{"dialogs":{"total":200,"correct":199},"responses":{"total":2358,"correct":2357}}},{"index":44400,"runtimeInSeconds":50333.269,"objectiveValue":-0.2675260837429858,"trainingStats":{"dialogs":{"total":200,"correct":200},"responses":{"total":2434,"correct":2434}},"devStats":{"dialogs":{"total":200,"correct":198},"responses":{"total":2358,"correct":2356}}},{"index":44600,"runtimeInSeconds":50559.184,"objectiveValue":-0.12183119498953572,"trainingStats":{"dialogs":{"total":200,"correct":200},"responses":{"total":2434,"correct":2434}},"devStats":{"dialogs":{"total":200,"correct":200},"responses":{"total":2358,"correct":2358}}},{"index":44800,"runtimeInSeconds":50779.95,"objectiveValue":-0.1604268634710116,"trainingStats":{"dialogs":{"total":200,"correct":200},"responses":{"total":2434,"correct":2434}},"devStats":{"dialogs":{"total":200,"correct":200},"responses":{"total":2358,"correct":2358}}},{"index":45000,"runtimeInSeconds":51004.065,"objectiveValue":-0.19885335966392798,"trainingStats":{"dialogs":{"total":200,"correct":200},"responses":{"total":2434,"correct":2434}},"devStats":{"dialogs":{"total":200,"correct":200},"responses":{"total":2358,"correct":2358}}},{"index":45200,"runtimeInSeconds":51227.151,"objectiveValue":-0.14354672935307664,"trainingStats":{"dialogs":{"total":200,"correct":200},"responses":{"total":2434,"correct":2434}},"devStats":{"dialogs":{"total":200,"correct":197},"responses":{"total":2358,"correct":2355}}},{"index":45400,"runtimeInSeconds":51453.372,"objectiveValue":-0.20385222511810863,"trainingStats":{"dialogs":{"total":200,"correct":200},"responses":{"total":2434,"correct":2434}},"devStats":{"dialogs":{"total":200,"correct":200},"responses":{"total":2358,"correct":2358}}},{"index":45600,"runtimeInSeconds":51686.349,"objectiveValue":-0.16051340504384232,"trainingStats":{"dialogs":{"total":200,"correct":200},"responses":{"total":2434,"correct":2434}},"devStats":{"dialogs":{"total":200,"correct":199},"responses":{"total":2358,"correct":2357}}},{"index":45800,"runtimeInSeconds":51915.663,"objectiveValue":-0.09313783436745514,"trainingStats":{"dialogs":{"total":200,"correct":200},"responses":{"total":2434,"correct":2434}},"devStats":{"dialogs":{"total":200,"correct":198},"responses":{"total":2358,"correct":2356}}},{"index":46000,"runtimeInSeconds":52141.969,"objectiveValue":-4001.244572710756,"trainingStats":{"dialogs":{"total":200,"correct":89},"responses":{"total":2434,"correct":2308}},"devStats":{"dialogs":{"total":200,"correct":90},"responses":{"total":2358,"correct":2224}}},{"index":46200,"runtimeInSeconds":52370.317,"objectiveValue":-12.950368111192825,"trainingStats":{"dialogs":{"total":200,"correct":199},"responses":{"total":2434,"correct":2433}},"devStats":{"dialogs":{"total":200,"correct":196},"responses":{"total":2358,"correct":2354}}},{"index":46400,"runtimeInSeconds":52593.532,"objectiveValue":-2.548392520298893,"trainingStats":{"dialogs":{"total":200,"correct":200},"responses":{"total":2434,"correct":2434}},"devStats":{"dialogs":{"total":200,"correct":199},"responses":{"total":2358,"correct":2357}}},{"index":46600,"runtimeInSeconds":52826.897,"objectiveValue":-2.723052562311329,"trainingStats":{"dialogs":{"total":200,"correct":200},"responses":{"total":2434,"correct":2434}},"devStats":{"dialogs":{"total":200,"correct":196},"responses":{"total":2358,"correct":2354}}},{"index":46800,"runtimeInSeconds":53056.168,"objectiveValue":-1.0145275619440606,"trainingStats":{"dialogs":{"total":200,"correct":200},"responses":{"total":2434,"correct":2434}},"devStats":{"dialogs":{"total":200,"correct":198},"responses":{"total":2358,"correct":2356}}},{"index":47000,"runtimeInSeconds":53284.158,"objectiveValue":-2.247531499668583,"trainingStats":{"dialogs":{"total":200,"correct":200},"responses":{"total":2434,"correct":2434}},"devStats":{"dialogs":{"total":200,"correct":197},"responses":{"total":2358,"correct":2355}}},{"index":47200,"runtimeInSeconds":53510.654,"objectiveValue":-1.0316928845914473,"trainingStats":{"dialogs":{"total":200,"correct":199},"responses":{"total":2434,"correct":2433}},"devStats":{"dialogs":{"total":200,"correct":199},"responses":{"total":2358,"correct":2357}}},{"index":47400,"runtimeInSeconds":53736.695,"objectiveValue":-1.6339826479703148,"trainingStats":{"dialogs":{"total":200,"correct":200},"responses":{"total":2434,"correct":2434}},"devStats":{"dialogs":{"total":200,"correct":200},"responses":{"total":2358,"correct":2358}}},{"index":47600,"runtimeInSeconds":53961.899,"objectiveValue":-1.945880105149099,"trainingStats":{"dialogs":{"total":200,"correct":200},"responses":{"total":2434,"correct":2434}},"devStats":{"dialogs":{"total":200,"correct":199},"responses":{"total":2358,"correct":2357}}},{"index":47800,"runtimeInSeconds":54188.478,"objectiveValue":-2.022230324560582,"trainingStats":{"dialogs":{"total":200,"correct":199},"responses":{"total":2434,"correct":2433}},"devStats":{"dialogs":{"total":200,"correct":200},"responses":{"total":2358,"correct":2358}}},{"index":48000,"runtimeInSeconds":54415.208,"objectiveValue":-0.6131863774778319,"trainingStats":{"dialogs":{"total":200,"correct":200},"responses":{"total":2434,"correct":2434}},"devStats":{"dialogs":{"total":200,"correct":199},"responses":{"total":2358,"correct":2357}}},{"index":48200,"runtimeInSeconds":54642.282,"objectiveValue":-0.49802391129398743,"trainingStats":{"dialogs":{"total":200,"correct":200},"responses":{"total":2434,"correct":2434}},"devStats":{"dialogs":{"total":200,"correct":199},"responses":{"total":2358,"correct":2357}}},{"index":48400,"runtimeInSeconds":54867.166,"objectiveValue":-0.31269413278245156,"trainingStats":{"dialogs":{"total":200,"correct":200},"responses":{"total":2434,"correct":2434}},"devStats":{"dialogs":{"total":200,"correct":199},"responses":{"total":2358,"correct":2357}}},{"index":48600,"runtimeInSeconds":55095.561,"objectiveValue":-0.5596640631815933,"trainingStats":{"dialogs":{"total":200,"correct":200},"responses":{"total":2434,"correct":2434}},"devStats":{"dialogs":{"total":200,"correct":199},"responses":{"total":2358,"correct":2357}}},{"index":48800,"runtimeInSeconds":55319.648,"objectiveValue":-0.5845711635448841,"trainingStats":{"dialogs":{"total":200,"correct":200},"responses":{"total":2434,"correct":2434}},"devStats":{"dialogs":{"total":200,"correct":200},"responses":{"total":2358,"correct":2358}}},{"index":49000,"runtimeInSeconds":55544.091,"objectiveValue":-1.195816865378129,"trainingStats":{"dialogs":{"total":200,"correct":199},"responses":{"total":2434,"correct":2433}},"devStats":{"dialogs":{"total":200,"correct":200},"responses":{"total":2358,"correct":2358}}},{"index":49200,"runtimeInSeconds":55769.239,"objectiveValue":-0.4329880308146042,"trainingStats":{"dialogs":{"total":200,"correct":200},"responses":{"total":2434,"correct":2434}},"devStats":{"dialogs":{"total":200,"correct":198},"responses":{"total":2358,"correct":2356}}},{"index":49400,"runtimeInSeconds":55990.985,"objectiveValue":-0.6671974341672753,"trainingStats":{"dialogs":{"total":200,"correct":200},"responses":{"total":2434,"correct":2434}},"devStats":{"dialogs":{"total":200,"correct":199},"responses":{"total":2358,"correct":2357}}},{"index":49600,"runtimeInSeconds":56218.259,"objectiveValue":-1.1400253818060768,"trainingStats":{"dialogs":{"total":200,"correct":200},"responses":{"total":2434,"correct":2434}},"devStats":{"dialogs":{"total":200,"correct":198},"responses":{"total":2358,"correct":2356}}},{"index":49800,"runtimeInSeconds":56447.112,"objectiveValue":-0.2892704353064803,"trainingStats":{"dialogs":{"total":200,"correct":200},"responses":{"total":2434,"correct":2434}},"devStats":{"dialogs":{"total":200,"correct":199},"responses":{"total":2358,"correct":2357}}},{"index":50000,"runtimeInSeconds":56669.695,"objectiveValue":-0.37840595973415425,"trainingStats":{"dialogs":{"total":200,"correct":200},"responses":{"total":2434,"correct":2434}},"devStats":{"dialogs":{"total":200,"correct":200},"responses":{"total":2358,"correct":2358}}},{"index":50200,"runtimeInSeconds":56898.632,"objectiveValue":-0.37611831012595826,"trainingStats":{"dialogs":{"total":200,"correct":200},"responses":{"total":2434,"correct":2434}},"devStats":{"dialogs":{"total":200,"correct":200},"responses":{"total":2358,"correct":2358}}},{"index":50400,"runtimeInSeconds":57129.472,"objectiveValue":-0.36259097525556766,"trainingStats":{"dialogs":{"total":200,"correct":200},"responses":{"total":2434,"correct":2434}},"devStats":{"dialogs":{"total":200,"correct":200},"responses":{"total":2358,"correct":2358}}},{"index":50600,"runtimeInSeconds":57351.887,"objectiveValue":-0.15097589734832748,"trainingStats":{"dialogs":{"total":200,"correct":200},"responses":{"total":2434,"correct":2434}},"devStats":{"dialogs":{"total":200,"correct":200},"responses":{"total":2358,"correct":2358}}},{"index":50800,"runtimeInSeconds":57578.249,"objectiveValue":-0.15666295606783573,"trainingStats":{"dialogs":{"total":200,"correct":200},"responses":{"total":2434,"correct":2434}},"devStats":{"dialogs":{"total":200,"correct":200},"responses":{"total":2358,"correct":2358}}},{"index":51000,"runtimeInSeconds":57804.886,"objectiveValue":-0.2124187300673245,"trainingStats":{"dialogs":{"total":200,"correct":200},"responses":{"total":2434,"correct":2434}},"devStats":{"dialogs":{"total":200,"correct":199},"responses":{"total":2358,"correct":2357}}},{"index":51200,"runtimeInSeconds":58033.004,"objectiveValue":-0.42670280694191604,"trainingStats":{"dialogs":{"total":200,"correct":200},"responses":{"total":2434,"correct":2434}},"devStats":{"dialogs":{"total":200,"correct":200},"responses":{"total":2358,"correct":2358}}},{"index":51400,"runtimeInSeconds":58259.453,"objectiveValue":-0.3655031106180473,"trainingStats":{"dialogs":{"total":200,"correct":200},"responses":{"total":2434,"correct":2434}},"devStats":{"dialogs":{"total":200,"correct":200},"responses":{"total":2358,"correct":2358}}},{"index":51600,"runtimeInSeconds":58494.641,"objectiveValue":-0.11301411102549869,"trainingStats":{"dialogs":{"total":200,"correct":200},"responses":{"total":2434,"correct":2434}},"devStats":{"dialogs":{"total":200,"correct":198},"responses":{"total":2358,"correct":2356}}},{"index":51800,"runtimeInSeconds":58717.761,"objectiveValue":-0.17298207578240357,"trainingStats":{"dialogs":{"total":200,"correct":200},"responses":{"total":2434,"correct":2434}},"devStats":{"dialogs":{"total":200,"correct":200},"responses":{"total":2358,"correct":2358}}},{"index":52000,"runtimeInSeconds":58945.118,"objectiveValue":-0.12249640915900929,"trainingStats":{"dialogs":{"total":200,"correct":200},"responses":{"total":2434,"correct":2434}},"devStats":{"dialogs":{"total":200,"correct":200},"responses":{"total":2358,"correct":2358}}},{"index":52200,"runtimeInSeconds":59175.713,"objectiveValue":-0.1215599313743047,"trainingStats":{"dialogs":{"total":200,"correct":200},"responses":{"total":2434,"correct":2434}},"devStats":{"dialogs":{"total":200,"correct":199},"responses":{"total":2358,"correct":2357}}},{"index":52400,"runtimeInSeconds":59401.106,"objectiveValue":-0.18769883343906868,"trainingStats":{"dialogs":{"total":200,"correct":200},"responses":{"total":2434,"correct":2434}},"devStats":{"dialogs":{"total":200,"correct":200},"responses":{"total":2358,"correct":2358}}},{"index":52600,"runtimeInSeconds":59625.091,"objectiveValue":-0.13520982712296226,"trainingStats":{"dialogs":{"total":200,"correct":200},"responses":{"total":2434,"correct":2434}},"devStats":{"dialogs":{"total":200,"correct":200},"responses":{"total":2358,"correct":2358}}},{"index":52800,"runtimeInSeconds":59858.189,"objectiveValue":-0.10620744737438884,"trainingStats":{"dialogs":{"total":200,"correct":200},"responses":{"total":2434,"correct":2434}},"devStats":{"dialogs":{"total":200,"correct":200},"responses":{"total":2358,"correct":2358}}},{"index":53000,"runtimeInSeconds":60084.177,"objectiveValue":-0.09941452904211842,"trainingStats":{"dialogs":{"total":200,"correct":200},"responses":{"total":2434,"correct":2434}},"devStats":{"dialogs":{"total":200,"correct":199},"responses":{"total":2358,"correct":2357}}},{"index":53200,"runtimeInSeconds":60317.901,"objectiveValue":-0.07359696645917835,"trainingStats":{"dialogs":{"total":200,"correct":200},"responses":{"total":2434,"correct":2434}},"devStats":{"dialogs":{"total":200,"correct":200},"responses":{"total":2358,"correct":2358}}},{"index":53400,"runtimeInSeconds":60548.244,"objectiveValue":-0.05408193323471699,"trainingStats":{"dialogs":{"total":200,"correct":200},"responses":{"total":2434,"correct":2434}},"devStats":{"dialogs":{"total":200,"correct":199},"responses":{"total":2358,"correct":2357}}},{"index":53600,"runtimeInSeconds":60771.57,"objectiveValue":-0.10218731623683028,"trainingStats":{"dialogs":{"total":200,"correct":200},"responses":{"total":2434,"correct":2434}},"devStats":{"dialogs":{"total":200,"correct":199},"responses":{"total":2358,"correct":2357}}},{"index":53800,"runtimeInSeconds":60998.425,"objectiveValue":-0.09448672074830011,"trainingStats":{"dialogs":{"total":200,"correct":200},"responses":{"total":2434,"correct":2434}},"devStats":{"dialogs":{"total":200,"correct":200},"responses":{"total":2358,"correct":2358}}},{"index":54000,"runtimeInSeconds":61224.576,"objectiveValue":-0.1108587896074698,"trainingStats":{"dialogs":{"total":200,"correct":200},"responses":{"total":2434,"correct":2434}},"devStats":{"dialogs":{"total":200,"correct":200},"responses":{"total":2358,"correct":2358}}},{"index":54200,"runtimeInSeconds":61450.95,"objectiveValue":-0.048686517240398276,"trainingStats":{"dialogs":{"total":200,"correct":200},"responses":{"total":2434,"correct":2434}},"devStats":{"dialogs":{"total":200,"correct":200},"responses":{"total":2358,"correct":2358}}},{"index":54400,"runtimeInSeconds":61673.431,"objectiveValue":-0.032685599005918387,"trainingStats":{"dialogs":{"total":200,"correct":200},"responses":{"total":2434,"correct":2434}},"devStats":{"dialogs":{"total":200,"correct":200},"responses":{"total":2358,"correct":2358}}},{"index":54600,"runtimeInSeconds":61899.502,"objectiveValue":-0.044022565780810985,"trainingStats":{"dialogs":{"total":200,"correct":200},"responses":{"total":2434,"correct":2434}},"devStats":{"dialogs":{"total":200,"correct":200},"responses":{"total":2358,"correct":2358}}},{"index":54800,"runtimeInSeconds":62125.306,"objectiveValue":-0.06674172317497545,"trainingStats":{"dialogs":{"total":200,"correct":200},"responses":{"total":2434,"correct":2434}},"devStats":{"dialogs":{"total":200,"correct":200},"responses":{"total":2358,"correct":2358}}},{"index":55000,"runtimeInSeconds":62352.88,"objectiveValue":-0.05835657538196506,"trainingStats":{"dialogs":{"total":200,"correct":200},"responses":{"total":2434,"correct":2434}},"devStats":{"dialogs":{"total":200,"correct":199},"responses":{"total":2358,"correct":2357}}},{"index":55200,"runtimeInSeconds":62572.954,"objectiveValue":-0.06606771293563526,"trainingStats":{"dialogs":{"total":200,"correct":200},"responses":{"total":2434,"correct":2434}},"devStats":{"dialogs":{"total":200,"correct":199},"responses":{"total":2358,"correct":2357}}},{"index":55400,"runtimeInSeconds":62799.074,"objectiveValue":-0.05166254001590054,"trainingStats":{"dialogs":{"total":200,"correct":200},"responses":{"total":2434,"correct":2434}},"devStats":{"dialogs":{"total":200,"correct":200},"responses":{"total":2358,"correct":2358}}},{"index":55600,"runtimeInSeconds":63023.03,"objectiveValue":-0.04020837602996651,"trainingStats":{"dialogs":{"total":200,"correct":200},"responses":{"total":2434,"correct":2434}},"devStats":{"dialogs":{"total":200,"correct":199},"responses":{"total":2358,"correct":2357}}},{"index":55800,"runtimeInSeconds":63247.534,"objectiveValue":-0.06298608622389436,"trainingStats":{"dialogs":{"total":200,"correct":200},"responses":{"total":2434,"correct":2434}},"devStats":{"dialogs":{"total":200,"correct":200},"responses":{"total":2358,"correct":2358}}},{"index":56000,"runtimeInSeconds":63475.614,"objectiveValue":-0.08690464014048369,"trainingStats":{"dialogs":{"total":200,"correct":200},"responses":{"total":2434,"correct":2434}},"devStats":{"dialogs":{"total":200,"correct":200},"responses":{"total":2358,"correct":2358}}},{"index":56200,"runtimeInSeconds":63700.292,"objectiveValue":-0.1019998034839332,"trainingStats":{"dialogs":{"total":200,"correct":200},"responses":{"total":2434,"correct":2434}},"devStats":{"dialogs":{"total":200,"correct":200},"responses":{"total":2358,"correct":2358}}}]